{"12117021502":{"TID":"12117021502","RID":0,"tEst":"24.9","rEst":"24.3","tMar":"6.77","rMar":"4.05","tCV":"0.165","rCV":"0.101","tMarMin":18.13,"tMarMax":31.67,"rMarMin":20.25,"rMarMax":28.35},"12117021401":{"TID":"12117021401","RID":0,"tEst":"23.8","rEst":"24.3","tMar":"4.88","rMar":"4.05","tCV":"0.125","rCV":"0.101","tMarMin":18.92,"tMarMax":28.68,"rMarMin":20.25,"rMarMax":28.35},"12117021806":{"TID":"12117021806","RID":1,"tEst":"25.5","rEst":"25.4","tMar":"5.89","rMar":"4.84","tCV":"0.141","rCV":"0.116","tMarMin":19.61,"tMarMax":31.39,"rMarMin":20.56,"rMarMax":30.24},"12117021803":{"TID":"12117021803","RID":1,"tEst":"25.4","rEst":"25.4","tMar":"8.46","rMar":"4.84","tCV":"0.203","rCV":"0.116","tMarMin":16.94,"tMarMax":33.86,"rMarMin":20.56,"rMarMax":30.24},"12095017017":{"TID":"12095017017","RID":2,"tEst":"22.3","rEst":"24.9","tMar":"7.2","rMar":"3.88","tCV":"0.196","rCV":"0.0949","tMarMin":15.1,"tMarMax":29.5,"rMarMin":21.02,"rMarMax":28.78},"12095017107":{"TID":"12095017107","RID":2,"tEst":"24.7","rEst":"24.9","tMar":"4.98","rMar":"3.88","tCV":"0.123","rCV":"0.0949","tMarMin":19.72,"tMarMax":29.68,"rMarMin":21.02,"rMarMax":28.78},"12097040804":{"TID":"12097040804","RID":2,"tEst":"25.9","rEst":"24.9","tMar":"9.89","rMar":"3.88","tCV":"0.232","rCV":"0.0949","tMarMin":16.01,"tMarMax":35.79,"rMarMin":21.02,"rMarMax":28.78},"12097040901":{"TID":"12097040901","RID":2,"tEst":"29.9","rEst":"24.9","tMar":"11.8","rMar":"3.88","tCV":"0.239","rCV":"0.0949","tMarMin":18.1,"tMarMax":41.7,"rMarMin":21.02,"rMarMax":28.78},"12069030102":{"TID":"12069030102","RID":3,"tEst":"38.7","rEst":"35.1","tMar":"16.5","rMar":"5.8","tCV":"0.259","rCV":"0.1","tMarMin":22.2,"tMarMax":55.2,"rMarMin":29.3,"rMarMax":40.9},"12069030104":{"TID":"12069030104","RID":3,"tEst":"34","rEst":"35.1","tMar":"15.9","rMar":"5.8","tCV":"0.284","rCV":"0.1","tMarMin":18.1,"tMarMax":49.9,"rMarMin":29.3,"rMarMax":40.9},"12069030107":{"TID":"12069030107","RID":3,"tEst":"32.6","rEst":"35.1","tMar":"9.7","rMar":"5.8","tCV":"0.181","rCV":"0.1","tMarMin":22.9,"tMarMax":42.3,"rMarMin":29.3,"rMarMax":40.9},"12069030106":{"TID":"12069030106","RID":3,"tEst":"38.5","rEst":"35.1","tMar":"17.5","rMar":"5.8","tCV":"0.276","rCV":"0.1","tMarMin":21,"tMarMax":56,"rMarMin":29.3,"rMarMax":40.9},"12069030108":{"TID":"12069030108","RID":3,"tEst":"34.8","rEst":"35.1","tMar":"9.6","rMar":"5.8","tCV":"0.168","rCV":"0.1","tMarMin":25.2,"tMarMax":44.4,"rMarMin":29.3,"rMarMax":40.9},"12095018900":{"TID":"12095018900","RID":4,"tEst":"18.9","rEst":"27.8","tMar":"4.27","rMar":"2.61","tCV":"0.138","rCV":"0.0569","tMarMin":14.63,"tMarMax":23.17,"rMarMin":25.19,"rMarMax":30.41},"12095012000":{"TID":"12095012000","RID":4,"tEst":"29.6","rEst":"27.8","tMar":"6.11","rMar":"2.61","tCV":"0.126","rCV":"0.0569","tMarMin":23.49,"tMarMax":35.71,"rMarMin":25.19,"rMarMax":30.41},"12095010500":{"TID":"12095010500","RID":4,"tEst":"35.5","rEst":"27.8","tMar":"28.7","rMar":"2.61","tCV":"0.491","rCV":"0.0569","tMarMin":6.8,"tMarMax":64.2,"rMarMin":25.19,"rMarMax":30.41},"12095018300":{"TID":"12095018300","RID":4,"tEst":"22.5","rEst":"27.8","tMar":"7.95","rMar":"2.61","tCV":"0.214","rCV":"0.0569","tMarMin":14.55,"tMarMax":30.45,"rMarMin":25.19,"rMarMax":30.41},"12095018700":{"TID":"12095018700","RID":4,"tEst":"27.8","rEst":"27.8","tMar":"7.08","rMar":"2.61","tCV":"0.155","rCV":"0.0569","tMarMin":20.72,"tMarMax":34.88,"rMarMin":25.19,"rMarMax":30.41},"12095011701":{"TID":"12095011701","RID":4,"tEst":"30.2","rEst":"27.8","tMar":"9.56","rMar":"2.61","tCV":"0.193","rCV":"0.0569","tMarMin":20.64,"tMarMax":39.76,"rMarMin":25.19,"rMarMax":30.41},"12095010400":{"TID":"12095010400","RID":4,"tEst":"25.9","rEst":"27.8","tMar":"11.4","rMar":"2.61","tCV":"0.268","rCV":"0.0569","tMarMin":14.5,"tMarMax":37.3,"rMarMin":25.19,"rMarMax":30.41},"12095011702":{"TID":"12095011702","RID":4,"tEst":"32.9","rEst":"27.8","tMar":"10.7","rMar":"2.61","tCV":"0.198","rCV":"0.0569","tMarMin":22.2,"tMarMax":43.6,"rMarMin":25.19,"rMarMax":30.41},"12095014701":{"TID":"12095014701","RID":4,"tEst":"30.1","rEst":"27.8","tMar":"8.11","rMar":"2.61","tCV":"0.164","rCV":"0.0569","tMarMin":21.99,"tMarMax":38.21,"rMarMin":25.19,"rMarMax":30.41},"12095014601":{"TID":"12095014601","RID":4,"tEst":"33","rEst":"27.8","tMar":"9.28","rMar":"2.61","tCV":"0.171","rCV":"0.0569","tMarMin":23.72,"tMarMax":42.28,"rMarMin":25.19,"rMarMax":30.41},"12095014605":{"TID":"12095014605","RID":4,"tEst":"25.5","rEst":"27.8","tMar":"7.17","rMar":"2.61","tCV":"0.171","rCV":"0.0569","tMarMin":18.33,"tMarMax":32.67,"rMarMin":25.19,"rMarMax":30.41},"12117021615":{"TID":"12117021615","RID":5,"tEst":"28","rEst":"30.7","tMar":"9.41","rMar":"4.73","tCV":"0.205","rCV":"0.0936","tMarMin":18.59,"tMarMax":37.41,"rMarMin":25.97,"rMarMax":35.43},"12117021612":{"TID":"12117021612","RID":5,"tEst":"27.9","rEst":"30.7","tMar":"6.21","rMar":"4.73","tCV":"0.135","rCV":"0.0936","tMarMin":21.69,"tMarMax":34.11,"rMarMin":25.97,"rMarMax":35.43},"12117021611":{"TID":"12117021611","RID":5,"tEst":"34.5","rEst":"30.7","tMar":"8.5","rMar":"4.73","tCV":"0.15","rCV":"0.0936","tMarMin":26,"tMarMax":43,"rMarMin":25.97,"rMarMax":35.43},"12069030408":{"TID":"12069030408","RID":6,"tEst":"17.4","rEst":"20.6","tMar":"9.04","rMar":"3.83","tCV":"0.317","rCV":"0.113","tMarMin":8.36,"tMarMax":26.44,"rMarMin":16.77,"rMarMax":24.43},"12069030407":{"TID":"12069030407","RID":6,"tEst":"21.8","rEst":"20.6","tMar":"7.67","rMar":"3.83","tCV":"0.214","rCV":"0.113","tMarMin":14.13,"tMarMax":29.47,"rMarMin":16.77,"rMarMax":24.43},"12069030411":{"TID":"12069030411","RID":6,"tEst":"22.7","rEst":"20.6","tMar":"12.1","rMar":"3.83","tCV":"0.324","rCV":"0.113","tMarMin":10.6,"tMarMax":34.8,"rMarMin":16.77,"rMarMax":24.43},"12069030409":{"TID":"12069030409","RID":6,"tEst":"15.9","rEst":"20.6","tMar":"7.06","rMar":"3.83","tCV":"0.27","rCV":"0.113","tMarMin":8.84,"tMarMax":22.96,"rMarMin":16.77,"rMarMax":24.43},"12069030405":{"TID":"12069030405","RID":6,"tEst":"21.1","rEst":"20.6","tMar":"5.57","rMar":"3.83","tCV":"0.16","rCV":"0.113","tMarMin":15.53,"tMarMax":26.67,"rMarMin":16.77,"rMarMax":24.43},"12095016732":{"TID":"12095016732","RID":7,"tEst":"28.9","rEst":"28.6","tMar":"4.16","rMar":"3.78","tCV":"0.0876","rCV":"0.0803","tMarMin":24.74,"tMarMax":33.06,"rMarMin":24.82,"rMarMax":32.38},"12095016731":{"TID":"12095016731","RID":7,"tEst":"27.5","rEst":"28.6","tMar":"9.03","rMar":"3.78","tCV":"0.2","rCV":"0.0803","tMarMin":18.47,"tMarMax":36.53,"rMarMin":24.82,"rMarMax":32.38},"12095016714":{"TID":"12095016714","RID":8,"tEst":"28.5","rEst":"27.4","tMar":"7.02","rMar":"4.57","tCV":"0.15","rCV":"0.101","tMarMin":21.48,"tMarMax":35.52,"rMarMin":22.83,"rMarMax":31.97},"12095016716":{"TID":"12095016716","RID":8,"tEst":"26.8","rEst":"27.4","tMar":"5.92","rMar":"4.57","tCV":"0.134","rCV":"0.101","tMarMin":20.88,"tMarMax":32.72,"rMarMin":22.83,"rMarMax":31.97},"12095013505":{"TID":"12095013505","RID":9,"tEst":"28.7","rEst":"26.8","tMar":"8.94","rMar":"3.65","tCV":"0.189","rCV":"0.0827","tMarMin":19.76,"tMarMax":37.64,"rMarMin":23.15,"rMarMax":30.45},"12095013503":{"TID":"12095013503","RID":9,"tEst":"26.9","rEst":"26.8","tMar":"7.79","rMar":"3.65","tCV":"0.176","rCV":"0.0827","tMarMin":19.11,"tMarMax":34.69,"rMarMin":23.15,"rMarMax":30.45},"12095013405":{"TID":"12095013405","RID":9,"tEst":"29.5","rEst":"26.8","tMar":"16.4","rMar":"3.65","tCV":"0.337","rCV":"0.0827","tMarMin":13.1,"tMarMax":45.9,"rMarMin":23.15,"rMarMax":30.45},"12095013509":{"TID":"12095013509","RID":9,"tEst":"19.3","rEst":"26.8","tMar":"7.16","rMar":"3.65","tCV":"0.226","rCV":"0.0827","tMarMin":12.14,"tMarMax":26.46,"rMarMin":23.15,"rMarMax":30.45},"12095013508":{"TID":"12095013508","RID":9,"tEst":"29.2","rEst":"26.8","tMar":"10","rMar":"3.65","tCV":"0.209","rCV":"0.0827","tMarMin":19.2,"tMarMax":39.2,"rMarMin":23.15,"rMarMax":30.45},"12095013511":{"TID":"12095013511","RID":9,"tEst":"25.2","rEst":"26.8","tMar":"6.3","rMar":"3.65","tCV":"0.152","rCV":"0.0827","tMarMin":18.9,"tMarMax":31.5,"rMarMin":23.15,"rMarMax":30.45},"12095013510":{"TID":"12095013510","RID":9,"tEst":"26.3","rEst":"26.8","tMar":"9.34","rMar":"3.65","tCV":"0.216","rCV":"0.0827","tMarMin":16.96,"tMarMax":35.64,"rMarMin":23.15,"rMarMax":30.45},"12117022201":{"TID":"12117022201","RID":10,"tEst":"23.9","rEst":"26.2","tMar":"4.8","rMar":"4.69","tCV":"0.122","rCV":"0.109","tMarMin":19.1,"tMarMax":28.7,"rMarMin":21.51,"rMarMax":30.89},"12117022004":{"TID":"12117022004","RID":10,"tEst":"30.4","rEst":"26.2","tMar":"9.88","rMar":"4.69","tCV":"0.198","rCV":"0.109","tMarMin":20.52,"tMarMax":40.28,"rMarMin":21.51,"rMarMax":30.89},"12097042602":{"TID":"12097042602","RID":11,"tEst":"29.1","rEst":"29.1","tMar":"4.94","rMar":"4.94","tCV":"0.103","rCV":"0.103","tMarMin":24.16,"tMarMax":34.04,"rMarMin":24.16,"rMarMax":34.04},"12117021901":{"TID":"12117021901","RID":12,"tEst":"23.9","rEst":"23.7","tMar":"5.95","rMar":"4.43","tCV":"0.151","rCV":"0.114","tMarMin":17.95,"tMarMax":29.85,"rMarMin":19.27,"rMarMax":28.13},"12117021902":{"TID":"12117021902","RID":12,"tEst":"23.5","rEst":"23.7","tMar":"6.64","rMar":"4.43","tCV":"0.171","rCV":"0.114","tMarMin":16.86,"tMarMax":30.14,"rMarMin":19.27,"rMarMax":28.13},"12095013801":{"TID":"12095013801","RID":13,"tEst":"19.5","rEst":"20.3","tMar":"4.94","rMar":"3.7","tCV":"0.154","rCV":"0.111","tMarMin":14.56,"tMarMax":24.44,"rMarMin":16.6,"rMarMax":24},"12095013802":{"TID":"12095013802","RID":13,"tEst":"21","rEst":"20.3","tMar":"5.43","rMar":"3.7","tCV":"0.157","rCV":"0.111","tMarMin":15.57,"tMarMax":26.43,"rMarMin":16.6,"rMarMax":24},"12095012600":{"TID":"12095012600","RID":14,"tEst":"17.6","rEst":"17.6","tMar":"3.19","rMar":"3.19","tCV":"0.111","rCV":"0.111","tMarMin":14.41,"tMarMax":20.79,"rMarMin":14.41,"rMarMax":20.79},"12069031203":{"TID":"12069031203","RID":15,"tEst":"32","rEst":"32.7","tMar":"11.8","rMar":"6.12","tCV":"0.224","rCV":"0.114","tMarMin":20.2,"tMarMax":43.8,"rMarMin":26.58,"rMarMax":38.82},"12069031202":{"TID":"12069031202","RID":15,"tEst":"32.3","rEst":"32.7","tMar":"7.48","rMar":"6.12","tCV":"0.141","rCV":"0.114","tMarMin":24.82,"tMarMax":39.78,"rMarMin":26.58,"rMarMax":38.82},"12069031205":{"TID":"12069031205","RID":15,"tEst":"34.2","rEst":"32.7","tMar":"15.9","rMar":"6.12","tCV":"0.283","rCV":"0.114","tMarMin":18.3,"tMarMax":50.1,"rMarMin":26.58,"rMarMax":38.82},"12095016601":{"TID":"12095016601","RID":16,"tEst":"35.1","rEst":"35.2","tMar":"5.85","rMar":"4.63","tCV":"0.101","rCV":"0.0799","tMarMin":29.25,"tMarMax":40.95,"rMarMin":30.57,"rMarMax":39.83},"12117021204":{"TID":"12117021204","RID":16,"tEst":"35.4","rEst":"35.2","tMar":"7.51","rMar":"4.63","tCV":"0.129","rCV":"0.0799","tMarMin":27.89,"tMarMax":42.91,"rMarMin":30.57,"rMarMax":39.83},"12117021100":{"TID":"12117021100","RID":17,"tEst":"30.3","rEst":"29.3","tMar":"6.94","rMar":"5.46","tCV":"0.139","rCV":"0.113","tMarMin":23.36,"tMarMax":37.24,"rMarMin":23.84,"rMarMax":34.76},"12117020202":{"TID":"12117020202","RID":17,"tEst":"28.5","rEst":"29.3","tMar":"8.09","rMar":"5.46","tCV":"0.173","rCV":"0.113","tMarMin":20.41,"tMarMax":36.59,"rMarMin":23.84,"rMarMax":34.76},"12117021312":{"TID":"12117021312","RID":18,"tEst":"26.4","rEst":"27.2","tMar":"6.38","rMar":"4.88","tCV":"0.147","rCV":"0.109","tMarMin":20.02,"tMarMax":32.78,"rMarMin":22.32,"rMarMax":32.08},"12117021321":{"TID":"12117021321","RID":18,"tEst":"28.2","rEst":"27.2","tMar":"7.55","rMar":"4.88","tCV":"0.163","rCV":"0.109","tMarMin":20.65,"tMarMax":35.75,"rMarMin":22.32,"rMarMax":32.08},"12117020600":{"TID":"12117020600","RID":19,"tEst":"23.8","rEst":"24.3","tMar":"3.75","rMar":"3.36","tCV":"0.0958","rCV":"0.0842","tMarMin":20.05,"tMarMax":27.55,"rMarMin":20.94,"rMarMax":27.66},"12117020402":{"TID":"12117020402","RID":19,"tEst":"26.2","rEst":"24.3","tMar":"7.42","rMar":"3.36","tCV":"0.172","rCV":"0.0842","tMarMin":18.78,"tMarMax":33.62,"rMarMin":20.94,"rMarMax":27.66},"12117021614":{"TID":"12117021614","RID":20,"tEst":"25.1","rEst":"24.6","tMar":"6.53","rMar":"4.62","tCV":"0.158","rCV":"0.114","tMarMin":18.57,"tMarMax":31.63,"rMarMin":19.98,"rMarMax":29.22},"12117021608":{"TID":"12117021608","RID":20,"tEst":"24","rEst":"24.6","tMar":"6.54","rMar":"4.62","tCV":"0.165","rCV":"0.114","tMarMin":17.46,"tMarMax":30.54,"rMarMin":19.98,"rMarMax":29.22},"12095016733":{"TID":"12095016733","RID":21,"tEst":"29.3","rEst":"25.1","tMar":"10.3","rMar":"3.63","tCV":"0.214","rCV":"0.088","tMarMin":19,"tMarMax":39.6,"rMarMin":21.47,"rMarMax":28.73},"12095013507":{"TID":"12095013507","RID":21,"tEst":"23.3","rEst":"25.1","tMar":"5.43","rMar":"3.63","tCV":"0.141","rCV":"0.088","tMarMin":17.87,"tMarMax":28.73,"rMarMin":21.47,"rMarMax":28.73},"12095013606":{"TID":"12095013606","RID":21,"tEst":"24.7","rEst":"25.1","tMar":"6.29","rMar":"3.63","tCV":"0.155","rCV":"0.088","tMarMin":18.41,"tMarMax":30.99,"rMarMin":21.47,"rMarMax":28.73},"12095013512":{"TID":"12095013512","RID":21,"tEst":"23.4","rEst":"25.1","tMar":"6.2","rMar":"3.63","tCV":"0.161","rCV":"0.088","tMarMin":17.2,"tMarMax":29.6,"rMarMin":21.47,"rMarMax":28.73},"12095013402":{"TID":"12095013402","RID":22,"tEst":"23.8","rEst":"26.1","tMar":"7.82","rMar":"4.79","tCV":"0.2","rCV":"0.111","tMarMin":15.98,"tMarMax":31.62,"rMarMin":21.31,"rMarMax":30.89},"12095016715":{"TID":"12095016715","RID":22,"tEst":"27","rEst":"26.1","tMar":"5.91","rMar":"4.79","tCV":"0.133","rCV":"0.111","tMarMin":21.09,"tMarMax":32.91,"rMarMin":21.31,"rMarMax":30.89},"12069030504":{"TID":"12069030504","RID":23,"tEst":"19.4","rEst":"18.9","tMar":"5.98","rMar":"3.61","tCV":"0.188","rCV":"0.116","tMarMin":13.42,"tMarMax":25.38,"rMarMin":15.29,"rMarMax":22.51},"12069030602":{"TID":"12069030602","RID":23,"tEst":"14.6","rEst":"18.9","tMar":"5.85","rMar":"3.61","tCV":"0.243","rCV":"0.116","tMarMin":8.75,"tMarMax":20.45,"rMarMin":15.29,"rMarMax":22.51},"12069030601":{"TID":"12069030601","RID":23,"tEst":"20.9","rEst":"18.9","tMar":"6.27","rMar":"3.61","tCV":"0.182","rCV":"0.116","tMarMin":14.63,"tMarMax":27.17,"rMarMin":15.29,"rMarMax":22.51},"12097041700":{"TID":"12097041700","RID":24,"tEst":"31.3","rEst":"28.8","tMar":"7.91","rMar":"4.66","tCV":"0.154","rCV":"0.0985","tMarMin":23.39,"tMarMax":39.21,"rMarMin":24.14,"rMarMax":33.46},"12097041800":{"TID":"12097041800","RID":24,"tEst":"24.8","rEst":"28.8","tMar":"7.46","rMar":"4.66","tCV":"0.183","rCV":"0.0985","tMarMin":17.34,"tMarMax":32.26,"rMarMin":24.14,"rMarMax":33.46},"12097041600":{"TID":"12097041600","RID":24,"tEst":"29","rEst":"28.8","tMar":"8.14","rMar":"4.66","tCV":"0.171","rCV":"0.0985","tMarMin":20.86,"tMarMax":37.14,"rMarMin":24.14,"rMarMax":33.46},"12095013701":{"TID":"12095013701","RID":25,"tEst":"24.2","rEst":"24.9","tMar":"6.16","rMar":"3.52","tCV":"0.155","rCV":"0.0861","tMarMin":18.04,"tMarMax":30.36,"rMarMin":21.38,"rMarMax":28.42},"12095013603":{"TID":"12095013603","RID":25,"tEst":"23.5","rEst":"24.9","tMar":"5.87","rMar":"3.52","tCV":"0.152","rCV":"0.0861","tMarMin":17.63,"tMarMax":29.37,"rMarMin":21.38,"rMarMax":28.42},"12095013403":{"TID":"12095013403","RID":25,"tEst":"25.3","rEst":"24.9","tMar":"5.84","rMar":"3.52","tCV":"0.14","rCV":"0.0861","tMarMin":19.46,"tMarMax":31.14,"rMarMin":21.38,"rMarMax":28.42},"12095013406":{"TID":"12095013406","RID":25,"tEst":"27.4","rEst":"24.9","tMar":"10.5","rMar":"3.52","tCV":"0.232","rCV":"0.0861","tMarMin":16.9,"tMarMax":37.9,"rMarMin":21.38,"rMarMax":28.42},"12095016412":{"TID":"12095016412","RID":26,"tEst":"33.2","rEst":"30.3","tMar":"8.06","rMar":"5.65","tCV":"0.147","rCV":"0.113","tMarMin":25.14,"tMarMax":41.26,"rMarMin":24.65,"rMarMax":35.95},"12095016409":{"TID":"12095016409","RID":26,"tEst":"25.2","rEst":"30.3","tMar":"6.54","rMar":"5.65","tCV":"0.158","rCV":"0.113","tMarMin":18.66,"tMarMax":31.74,"rMarMin":24.65,"rMarMax":35.95},"12095016804":{"TID":"12095016804","RID":27,"tEst":"21.9","rEst":"21.9","tMar":"3.99","rMar":"3.99","tCV":"0.111","rCV":"0.111","tMarMin":17.91,"tMarMax":25.89,"rMarMin":17.91,"rMarMax":25.89},"12069030209":{"TID":"12069030209","RID":28,"tEst":"24.6","rEst":"28.6","tMar":"10.9","rMar":"5.4","tCV":"0.271","rCV":"0.115","tMarMin":13.7,"tMarMax":35.5,"rMarMin":23.2,"rMarMax":34},"12069030302":{"TID":"12069030302","RID":28,"tEst":"31.5","rEst":"28.6","tMar":"9.04","rMar":"5.4","tCV":"0.174","rCV":"0.115","tMarMin":22.46,"tMarMax":40.54,"rMarMin":23.2,"rMarMax":34},"12069030307":{"TID":"12069030307","RID":28,"tEst":"27.7","rEst":"28.6","tMar":"8.32","rMar":"5.4","tCV":"0.183","rCV":"0.115","tMarMin":19.38,"tMarMax":36.02,"rMarMin":23.2,"rMarMax":34},"12095014606":{"TID":"12095014606","RID":29,"tEst":"25.9","rEst":"25","tMar":"5.23","rMar":"1.92","tCV":"0.123","rCV":"0.0467","tMarMin":20.67,"tMarMax":31.13,"rMarMin":23.08,"rMarMax":26.92},"12095016904":{"TID":"12095016904","RID":29,"tEst":"24.8","rEst":"25","tMar":"8.92","rMar":"1.92","tCV":"0.218","rCV":"0.0467","tMarMin":15.88,"tMarMax":33.72,"rMarMin":23.08,"rMarMax":26.92},"12095014302":{"TID":"12095014302","RID":29,"tEst":"22.6","rEst":"25","tMar":"4.67","rMar":"1.92","tCV":"0.126","rCV":"0.0467","tMarMin":17.93,"tMarMax":27.27,"rMarMin":23.08,"rMarMax":26.92},"12095016902":{"TID":"12095016902","RID":29,"tEst":"26.3","rEst":"25","tMar":"7.1","rMar":"1.92","tCV":"0.164","rCV":"0.0467","tMarMin":19.2,"tMarMax":33.4,"rMarMin":23.08,"rMarMax":26.92},"12095011600":{"TID":"12095011600","RID":29,"tEst":"27","rEst":"25","tMar":"8.27","rMar":"1.92","tCV":"0.186","rCV":"0.0467","tMarMin":18.73,"tMarMax":35.27,"rMarMin":23.08,"rMarMax":26.92},"12095014503":{"TID":"12095014503","RID":29,"tEst":"26.6","rEst":"25","tMar":"11","rMar":"1.92","tCV":"0.251","rCV":"0.0467","tMarMin":15.6,"tMarMax":37.6,"rMarMin":23.08,"rMarMax":26.92},"12095016906":{"TID":"12095016906","RID":29,"tEst":"24.3","rEst":"25","tMar":"7.02","rMar":"1.92","tCV":"0.176","rCV":"0.0467","tMarMin":17.28,"tMarMax":31.32,"rMarMin":23.08,"rMarMax":26.92},"12095016907":{"TID":"12095016907","RID":29,"tEst":"25.3","rEst":"25","tMar":"6.12","rMar":"1.92","tCV":"0.147","rCV":"0.0467","tMarMin":19.18,"tMarMax":31.42,"rMarMin":23.08,"rMarMax":26.92},"12095016903":{"TID":"12095016903","RID":29,"tEst":"22","rEst":"25","tMar":"3.29","rMar":"1.92","tCV":"0.0908","rCV":"0.0467","tMarMin":18.71,"tMarMax":25.29,"rMarMin":23.08,"rMarMax":26.92},"12095014609":{"TID":"12095014609","RID":29,"tEst":"29.1","rEst":"25","tMar":"8.47","rMar":"1.92","tCV":"0.177","rCV":"0.0467","tMarMin":20.63,"tMarMax":37.57,"rMarMin":23.08,"rMarMax":26.92},"12095014502":{"TID":"12095014502","RID":29,"tEst":"25.9","rEst":"25","tMar":"6.44","rMar":"1.92","tCV":"0.151","rCV":"0.0467","tMarMin":19.46,"tMarMax":32.34,"rMarMin":23.08,"rMarMax":26.92},"12069030208":{"TID":"12069030208","RID":30,"tEst":"22.5","rEst":"23.3","tMar":"5.86","rMar":"3.94","tCV":"0.158","rCV":"0.103","tMarMin":16.64,"tMarMax":28.36,"rMarMin":19.36,"rMarMax":27.24},"12069030206":{"TID":"12069030206","RID":30,"tEst":"24.1","rEst":"23.3","tMar":"9.36","rMar":"3.94","tCV":"0.236","rCV":"0.103","tMarMin":14.74,"tMarMax":33.46,"rMarMin":19.36,"rMarMax":27.24},"12069030204":{"TID":"12069030204","RID":30,"tEst":"23.4","rEst":"23.3","tMar":"5.88","rMar":"3.94","tCV":"0.153","rCV":"0.103","tMarMin":17.52,"tMarMax":29.28,"rMarMin":19.36,"rMarMax":27.24},"12095017504":{"TID":"12095017504","RID":31,"tEst":"29.3","rEst":"26.9","tMar":"8.03","rMar":"4.17","tCV":"0.167","rCV":"0.0943","tMarMin":21.27,"tMarMax":37.33,"rMarMin":22.73,"rMarMax":31.07},"12117021708":{"TID":"12117021708","RID":31,"tEst":"25.4","rEst":"26.9","tMar":"5.23","rMar":"4.17","tCV":"0.125","rCV":"0.0943","tMarMin":20.17,"tMarMax":30.63,"rMarMin":22.73,"rMarMax":31.07},"12117021704":{"TID":"12117021704","RID":31,"tEst":"24.3","rEst":"26.9","tMar":"5.77","rMar":"4.17","tCV":"0.144","rCV":"0.0943","tMarMin":18.53,"tMarMax":30.07,"rMarMin":22.73,"rMarMax":31.07},"12117022205":{"TID":"12117022205","RID":32,"tEst":"29.1","rEst":"25.7","tMar":"8.36","rMar":"4.58","tCV":"0.175","rCV":"0.108","tMarMin":20.74,"tMarMax":37.46,"rMarMin":21.12,"rMarMax":30.28},"12117022002":{"TID":"12117022002","RID":32,"tEst":"23.5","rEst":"25.7","tMar":"5.25","rMar":"4.58","tCV":"0.136","rCV":"0.108","tMarMin":18.25,"tMarMax":28.75,"rMarMin":21.12,"rMarMax":30.28},"12117020701":{"TID":"12117020701","RID":33,"tEst":"27.4","rEst":"27.4","tMar":"4.47","rMar":"4.47","tCV":"0.0991","rCV":"0.0991","tMarMin":22.93,"tMarMax":31.87,"rMarMin":22.93,"rMarMax":31.87},"12117021604":{"TID":"12117021604","RID":34,"tEst":"25.3","rEst":"25.6","tMar":"4.62","rMar":"2.87","tCV":"0.111","rCV":"0.0682","tMarMin":20.68,"tMarMax":29.92,"rMarMin":22.73,"rMarMax":28.47},"12095017808":{"TID":"12095017808","RID":34,"tEst":"26.2","rEst":"25.6","tMar":"4.74","rMar":"2.87","tCV":"0.11","rCV":"0.0682","tMarMin":21.46,"tMarMax":30.94,"rMarMin":22.73,"rMarMax":28.47},"12117021609":{"TID":"12117021609","RID":34,"tEst":"25.1","rEst":"25.6","tMar":"5.68","rMar":"2.87","tCV":"0.137","rCV":"0.0682","tMarMin":19.42,"tMarMax":30.78,"rMarMin":22.73,"rMarMax":28.47},"12117021307":{"TID":"12117021307","RID":35,"tEst":"27.4","rEst":"28","tMar":"5.78","rMar":"4.75","tCV":"0.128","rCV":"0.103","tMarMin":21.62,"tMarMax":33.18,"rMarMin":23.25,"rMarMax":32.75},"12117021318":{"TID":"12117021318","RID":35,"tEst":"28.6","rEst":"28","tMar":"7.68","rMar":"4.75","tCV":"0.163","rCV":"0.103","tMarMin":20.92,"tMarMax":36.28,"rMarMin":23.25,"rMarMax":32.75},"12095016408":{"TID":"12095016408","RID":36,"tEst":"23.5","rEst":"23.2","tMar":"6.06","rMar":"3.44","tCV":"0.157","rCV":"0.0902","tMarMin":17.44,"tMarMax":29.56,"rMarMin":19.76,"rMarMax":26.64},"12117022207":{"TID":"12117022207","RID":36,"tEst":"22.1","rEst":"23.2","tMar":"5.46","rMar":"3.44","tCV":"0.15","rCV":"0.0902","tMarMin":16.64,"tMarMax":27.56,"rMarMin":19.76,"rMarMax":26.64},"12117022209":{"TID":"12117022209","RID":36,"tEst":"24.6","rEst":"23.2","tMar":"5.81","rMar":"3.44","tCV":"0.143","rCV":"0.0902","tMarMin":18.79,"tMarMax":30.41,"rMarMin":19.76,"rMarMax":26.64},"12095016802":{"TID":"12095016802","RID":37,"tEst":"23.1","rEst":"23.1","tMar":"3.96","rMar":"3.96","tCV":"0.104","rCV":"0.104","tMarMin":19.14,"tMarMax":27.06,"rMarMin":19.14,"rMarMax":27.06},"12097042900":{"TID":"12097042900","RID":38,"tEst":"28.8","rEst":"28.5","tMar":"4.78","rMar":"3.98","tCV":"0.101","rCV":"0.0848","tMarMin":24.02,"tMarMax":33.58,"rMarMin":24.52,"rMarMax":32.48},"12097043203":{"TID":"12097043203","RID":38,"tEst":"27.7","rEst":"28.5","tMar":"6.39","rMar":"3.98","tCV":"0.14","rCV":"0.0848","tMarMin":21.31,"tMarMax":34.09,"rMarMin":24.52,"rMarMax":32.48},"12095016406":{"TID":"12095016406","RID":39,"tEst":"25.1","rEst":"24.8","tMar":"7.25","rMar":"4.09","tCV":"0.176","rCV":"0.1","tMarMin":17.85,"tMarMax":32.35,"rMarMin":20.71,"rMarMax":28.89},"12095013201":{"TID":"12095013201","RID":39,"tEst":"22.6","rEst":"24.8","tMar":"6.13","rMar":"4.09","tCV":"0.165","rCV":"0.1","tMarMin":16.47,"tMarMax":28.73,"rMarMin":20.71,"rMarMax":28.89},"12095016402":{"TID":"12095016402","RID":39,"tEst":"27.3","rEst":"24.8","tMar":"7.73","rMar":"4.09","tCV":"0.172","rCV":"0.1","tMarMin":19.57,"tMarMax":35.03,"rMarMin":20.71,"rMarMax":28.89},"12095017013":{"TID":"12095017013","RID":40,"tEst":"24.7","rEst":"24.7","tMar":"4.61","rMar":"4.61","tCV":"0.114","rCV":"0.114","tMarMin":20.09,"tMarMax":29.31,"rMarMin":20.09,"rMarMax":29.31},"12117021320":{"TID":"12117021320","RID":41,"tEst":"28","rEst":"26.2","tMar":"5.47","rMar":"4.13","tCV":"0.119","rCV":"0.0959","tMarMin":22.53,"tMarMax":33.47,"rMarMin":22.07,"rMarMax":30.33},"12117021314":{"TID":"12117021314","RID":41,"tEst":"22.3","rEst":"26.2","tMar":"5.71","rMar":"4.13","tCV":"0.155","rCV":"0.0959","tMarMin":16.59,"tMarMax":28.01,"rMarMin":22.07,"rMarMax":30.33},"12095016511":{"TID":"12095016511","RID":42,"tEst":"21.9","rEst":"25.5","tMar":"7.74","rMar":"4.6","tCV":"0.215","rCV":"0.11","tMarMin":14.16,"tMarMax":29.64,"rMarMin":20.9,"rMarMax":30.1},"12095016505":{"TID":"12095016505","RID":42,"tEst":"26.7","rEst":"25.5","tMar":"9.01","rMar":"4.6","tCV":"0.205","rCV":"0.11","tMarMin":17.69,"tMarMax":35.71,"rMarMin":20.9,"rMarMax":30.1},"12095016727":{"TID":"12095016727","RID":42,"tEst":"26.5","rEst":"25.5","tMar":"6.59","rMar":"4.6","tCV":"0.151","rCV":"0.11","tMarMin":19.91,"tMarMax":33.09,"rMarMin":20.9,"rMarMax":30.1},"12097043204":{"TID":"12097043204","RID":43,"tEst":"27.7","rEst":"28.8","tMar":"4.99","rMar":"0","tCV":"0.11","rCV":"0","tMarMin":22.71,"tMarMax":32.69,"rMarMin":28.8,"rMarMax":28.8},"12097043202":{"TID":"12097043202","RID":43,"tEst":"73.2","rEst":"28.8","tMar":"89.5","rMar":"0","tCV":"0.743","rCV":"0","tMarMin":-16.3,"tMarMax":162.7,"rMarMin":28.8,"rMarMax":28.8},"12097043201":{"TID":"12097043201","RID":43,"tEst":"0","rEst":"28.8","tMar":"0","rMar":"0","tCV":"0","rCV":"0","tMarMin":0,"tMarMax":0,"rMarMin":28.8,"rMarMax":28.8},"12069031306":{"TID":"12069031306","RID":44,"tEst":"27","rEst":"27","tMar":"4.72","rMar":"4.72","tCV":"0.106","rCV":"0.106","tMarMin":22.28,"tMarMax":31.72,"rMarMin":22.28,"rMarMax":31.72},"12117021616":{"TID":"12117021616","RID":45,"tEst":"22.3","rEst":"23.9","tMar":"6.04","rMar":"4.44","tCV":"0.165","rCV":"0.113","tMarMin":16.26,"tMarMax":28.34,"rMarMin":19.46,"rMarMax":28.34},"12117020704":{"TID":"12117020704","RID":45,"tEst":"24.4","rEst":"23.9","tMar":"6.73","rMar":"4.44","tCV":"0.168","rCV":"0.113","tMarMin":17.67,"tMarMax":31.13,"rMarMin":19.46,"rMarMax":28.34},"12117020705":{"TID":"12117020705","RID":45,"tEst":"24.7","rEst":"23.9","tMar":"9.48","rMar":"4.44","tCV":"0.234","rCV":"0.113","tMarMin":15.22,"tMarMax":34.18,"rMarMin":19.46,"rMarMax":28.34},"12117022104":{"TID":"12117022104","RID":46,"tEst":"26.8","rEst":"26.6","tMar":"5.62","rMar":"4.54","tCV":"0.128","rCV":"0.104","tMarMin":21.18,"tMarMax":32.42,"rMarMin":22.06,"rMarMax":31.14},"12117022101":{"TID":"12117022101","RID":46,"tEst":"26.5","rEst":"26.6","tMar":"7.34","rMar":"4.54","tCV":"0.169","rCV":"0.104","tMarMin":19.16,"tMarMax":33.84,"rMarMin":22.06,"rMarMax":31.14},"12095016724":{"TID":"12095016724","RID":47,"tEst":"31.1","rEst":"29.6","tMar":"7.51","rMar":"4.77","tCV":"0.147","rCV":"0.098","tMarMin":23.59,"tMarMax":38.61,"rMarMin":24.83,"rMarMax":34.37},"12095016723":{"TID":"12095016723","RID":47,"tEst":"27.8","rEst":"29.6","tMar":"5.51","rMar":"4.77","tCV":"0.12","rCV":"0.098","tMarMin":22.29,"tMarMax":33.31,"rMarMin":24.83,"rMarMax":34.37},"12069030105":{"TID":"12069030105","RID":48,"tEst":"30.4","rEst":"29","tMar":"7.6","rMar":"5.52","tCV":"0.152","rCV":"0.116","tMarMin":22.8,"tMarMax":38,"rMarMin":23.48,"rMarMax":34.52},"12069030207":{"TID":"12069030207","RID":48,"tEst":"26.4","rEst":"29","tMar":"6.92","rMar":"5.52","tCV":"0.16","rCV":"0.116","tMarMin":19.48,"tMarMax":33.32,"rMarMin":23.48,"rMarMax":34.52},"12095014400":{"TID":"12095014400","RID":49,"tEst":"22","rEst":"22.9","tMar":"6.1","rMar":"4.28","tCV":"0.169","rCV":"0.114","tMarMin":15.9,"tMarMax":28.1,"rMarMin":18.62,"rMarMax":27.18},"12095014301":{"TID":"12095014301","RID":49,"tEst":"23.4","rEst":"22.9","tMar":"5.7","rMar":"4.28","tCV":"0.148","rCV":"0.114","tMarMin":17.7,"tMarMax":29.1,"rMarMin":18.62,"rMarMax":27.18},"12117021705":{"TID":"12117021705","RID":50,"tEst":"20.7","rEst":"21.4","tMar":"7.05","rMar":"3.98","tCV":"0.207","rCV":"0.113","tMarMin":13.65,"tMarMax":27.75,"rMarMin":17.42,"rMarMax":25.38},"12117021707":{"TID":"12117021707","RID":50,"tEst":"21.9","rEst":"21.4","tMar":"4.58","rMar":"3.98","tCV":"0.127","rCV":"0.113","tMarMin":17.32,"tMarMax":26.48,"rMarMin":17.42,"rMarMax":25.38},"12117020810":{"TID":"12117020810","RID":51,"tEst":"26","rEst":"24.9","tMar":"6.41","rMar":"4.32","tCV":"0.15","rCV":"0.105","tMarMin":19.59,"tMarMax":32.41,"rMarMin":20.58,"rMarMax":29.22},"12117020808":{"TID":"12117020808","RID":51,"tEst":"23.6","rEst":"24.9","tMar":"5.59","rMar":"4.32","tCV":"0.144","rCV":"0.105","tMarMin":18.01,"tMarMax":29.19,"rMarMin":20.58,"rMarMax":29.22},"12095017103":{"TID":"12095017103","RID":52,"tEst":"21.9","rEst":"22.7","tMar":"4.34","rMar":"3.01","tCV":"0.12","rCV":"0.0806","tMarMin":17.56,"tMarMax":26.24,"rMarMin":19.69,"rMarMax":25.71},"12097040803":{"TID":"12097040803","RID":52,"tEst":"22.5","rEst":"22.7","tMar":"5.44","rMar":"3.01","tCV":"0.147","rCV":"0.0806","tMarMin":17.06,"tMarMax":27.94,"rMarMin":19.69,"rMarMax":25.71},"12097040801":{"TID":"12097040801","RID":52,"tEst":"20.7","rEst":"22.7","tMar":"17.4","rMar":"3.01","tCV":"0.511","rCV":"0.0806","tMarMin":3.3,"tMarMax":38.1,"rMarMin":19.69,"rMarMax":25.71},"12097040802":{"TID":"12097040802","RID":52,"tEst":"24.9","rEst":"22.7","tMar":"6.83","rMar":"3.01","tCV":"0.167","rCV":"0.0806","tMarMin":18.07,"tMarMax":31.73,"rMarMin":19.69,"rMarMax":25.71},"12117022005":{"TID":"12117022005","RID":53,"tEst":"22.5","rEst":"22.8","tMar":"4.79","rMar":"3.89","tCV":"0.129","rCV":"0.103","tMarMin":17.71,"tMarMax":27.29,"rMarMin":18.91,"rMarMax":26.69},"12095015602":{"TID":"12095015602","RID":53,"tEst":"23.8","rEst":"22.8","tMar":"5.53","rMar":"3.89","tCV":"0.141","rCV":"0.103","tMarMin":18.27,"tMarMax":29.33,"rMarMin":18.91,"rMarMax":26.69},"12095017802":{"TID":"12095017802","RID":54,"tEst":"32.8","rEst":"32.8","tMar":"5.49","rMar":"5.49","tCV":"0.102","rCV":"0.102","tMarMin":27.31,"tMarMax":38.29,"rMarMin":27.31,"rMarMax":38.29},"12117021802":{"TID":"12117021802","RID":55,"tEst":"21.9","rEst":"23.7","tMar":"5.03","rMar":"4.51","tCV":"0.139","rCV":"0.116","tMarMin":16.87,"tMarMax":26.93,"rMarMin":19.19,"rMarMax":28.21},"12117022001":{"TID":"12117022001","RID":55,"tEst":"29.8","rEst":"23.7","tMar":"9.76","rMar":"4.51","tCV":"0.199","rCV":"0.116","tMarMin":20.04,"tMarMax":39.56,"rMarMin":19.19,"rMarMax":28.21},"12069031311":{"TID":"12069031311","RID":56,"tEst":"27.6","rEst":"27.6","tMar":"3.59","rMar":"3.59","tCV":"0.079","rCV":"0.079","tMarMin":24.01,"tMarMax":31.19,"rMarMin":24.01,"rMarMax":31.19},"12095011000":{"TID":"12095011000","RID":57,"tEst":"20.2","rEst":"20.2","tMar":"3.84","rMar":"3.84","tCV":"0.115","rCV":"0.115","tMarMin":16.36,"tMarMax":24.04,"rMarMin":16.36,"rMarMax":24.04},"12097043400":{"TID":"12097043400","RID":58,"tEst":"28.5","rEst":"28.5","tMar":"5.36","rMar":"5.36","tCV":"0.114","rCV":"0.114","tMarMin":23.14,"tMarMax":33.86,"rMarMin":23.14,"rMarMax":33.86},"12095018200":{"TID":"12095018200","RID":59,"tEst":"23.1","rEst":"23.1","tMar":"3.4","rMar":"3.4","tCV":"0.0896","rCV":"0.0896","tMarMin":19.7,"tMarMax":26.5,"rMarMin":19.7,"rMarMax":26.5},"12095014806":{"TID":"12095014806","RID":60,"tEst":"25.9","rEst":"25.9","tMar":"5.01","rMar":"5.01","tCV":"0.118","rCV":"0.118","tMarMin":20.89,"tMarMax":30.91,"rMarMin":20.89,"rMarMax":30.91},"12095016508":{"TID":"12095016508","RID":61,"tEst":"26.9","rEst":"25.6","tMar":"8.04","rMar":"4.46","tCV":"0.182","rCV":"0.106","tMarMin":18.86,"tMarMax":34.94,"rMarMin":21.14,"rMarMax":30.06},"12095016504":{"TID":"12095016504","RID":61,"tEst":"25.3","rEst":"25.6","tMar":"6.19","rMar":"4.46","tCV":"0.149","rCV":"0.106","tMarMin":19.11,"tMarMax":31.49,"rMarMin":21.14,"rMarMax":30.06},"12095016510":{"TID":"12095016510","RID":61,"tEst":"23.9","rEst":"25.6","tMar":"9.16","rMar":"4.46","tCV":"0.233","rCV":"0.106","tMarMin":14.74,"tMarMax":33.06,"rMarMin":21.14,"rMarMax":30.06},"12095012303":{"TID":"12095012303","RID":62,"tEst":"29.9","rEst":"30.9","tMar":"5.23","rMar":"3.85","tCV":"0.106","rCV":"0.0757","tMarMin":24.67,"tMarMax":35.13,"rMarMin":27.05,"rMarMax":34.75},"12095012304":{"TID":"12095012304","RID":62,"tEst":"33.6","rEst":"30.9","tMar":"7.67","rMar":"3.85","tCV":"0.139","rCV":"0.0757","tMarMin":25.93,"tMarMax":41.27,"rMarMin":27.05,"rMarMax":34.75},"12095014909":{"TID":"12095014909","RID":62,"tEst":"27.7","rEst":"30.9","tMar":"6.29","rMar":"3.85","tCV":"0.138","rCV":"0.0757","tMarMin":21.41,"tMarMax":33.99,"rMarMin":27.05,"rMarMax":34.75},"12095013604":{"TID":"12095013604","RID":63,"tEst":"25","rEst":"24.1","tMar":"5.87","rMar":"4.22","tCV":"0.143","rCV":"0.106","tMarMin":19.13,"tMarMax":30.87,"rMarMin":19.88,"rMarMax":28.32},"12095013803":{"TID":"12095013803","RID":63,"tEst":"22.3","rEst":"24.1","tMar":"5.14","rMar":"4.22","tCV":"0.14","rCV":"0.106","tMarMin":17.16,"tMarMax":27.44,"rMarMin":19.88,"rMarMax":28.32},"12069030804":{"TID":"12069030804","RID":64,"tEst":"17.6","rEst":"21.7","tMar":"13.5","rMar":"3.67","tCV":"0.465","rCV":"0.103","tMarMin":4.1,"tMarMax":31.1,"rMarMin":18.03,"rMarMax":25.37},"12069030913":{"TID":"12069030913","RID":64,"tEst":"21.4","rEst":"21.7","tMar":"11.5","rMar":"3.67","tCV":"0.327","rCV":"0.103","tMarMin":9.9,"tMarMax":32.9,"rMarMin":18.03,"rMarMax":25.37},"12069030803":{"TID":"12069030803","RID":64,"tEst":"21.7","rEst":"21.7","tMar":"8.47","rMar":"3.67","tCV":"0.237","rCV":"0.103","tMarMin":13.23,"tMarMax":30.17,"rMarMin":18.03,"rMarMax":25.37},"12069030806":{"TID":"12069030806","RID":64,"tEst":"19.7","rEst":"21.7","tMar":"7.48","rMar":"3.67","tCV":"0.231","rCV":"0.103","tMarMin":12.22,"tMarMax":27.18,"rMarMin":18.03,"rMarMax":25.37},"12069030807":{"TID":"12069030807","RID":64,"tEst":"19.9","rEst":"21.7","tMar":"6.32","rMar":"3.67","tCV":"0.193","rCV":"0.103","tMarMin":13.58,"tMarMax":26.22,"rMarMin":18.03,"rMarMax":25.37},"12069030912":{"TID":"12069030912","RID":64,"tEst":"24.2","rEst":"21.7","tMar":"7.33","rMar":"3.67","tCV":"0.184","rCV":"0.103","tMarMin":16.87,"tMarMax":31.53,"rMarMin":18.03,"rMarMax":25.37},"12117020811":{"TID":"12117020811","RID":65,"tEst":"25.5","rEst":"24.6","tMar":"6.02","rMar":"4.45","tCV":"0.143","rCV":"0.11","tMarMin":19.48,"tMarMax":31.52,"rMarMin":20.15,"rMarMax":29.05},"12117020812":{"TID":"12117020812","RID":65,"tEst":"23.2","rEst":"24.6","tMar":"6.48","rMar":"4.45","tCV":"0.17","rCV":"0.11","tMarMin":16.72,"tMarMax":29.68,"rMarMin":20.15,"rMarMax":29.05},"12095015702":{"TID":"12095015702","RID":66,"tEst":"21.6","rEst":"20.8","tMar":"4.74","rMar":"3.1","tCV":"0.133","rCV":"0.0907","tMarMin":16.86,"tMarMax":26.34,"rMarMin":17.7,"rMarMax":23.9},"12095015802":{"TID":"12095015802","RID":66,"tEst":"20.1","rEst":"20.8","tMar":"4.07","rMar":"3.1","tCV":"0.123","rCV":"0.0907","tMarMin":16.03,"tMarMax":24.17,"rMarMin":17.7,"rMarMax":23.9},"12097041300":{"TID":"12097041300","RID":67,"tEst":"37.7","rEst":"37.7","tMar":"6.01","rMar":"6.01","tCV":"0.0967","rCV":"0.0967","tMarMin":31.69,"tMarMax":43.71,"rMarMin":31.69,"rMarMax":43.71},"12095012500":{"TID":"12095012500","RID":68,"tEst":"20.6","rEst":"20.4","tMar":"5.3","rMar":"1.86","tCV":"0.157","rCV":"0.0555","tMarMin":15.3,"tMarMax":25.9,"rMarMin":18.54,"rMarMax":22.26},"12095018800":{"TID":"12095018800","RID":68,"tEst":"19.9","rEst":"20.4","tMar":"3.01","rMar":"1.86","tCV":"0.0922","rCV":"0.0555","tMarMin":16.89,"tMarMax":22.91,"rMarMin":18.54,"rMarMax":22.26},"12095012800":{"TID":"12095012800","RID":68,"tEst":"20.2","rEst":"20.4","tMar":"4.7","rMar":"1.86","tCV":"0.141","rCV":"0.0555","tMarMin":15.5,"tMarMax":24.9,"rMarMin":18.54,"rMarMax":22.26},"12095012701":{"TID":"12095012701","RID":68,"tEst":"20.9","rEst":"20.4","tMar":"3.9","rMar":"1.86","tCV":"0.113","rCV":"0.0555","tMarMin":17,"tMarMax":24.8,"rMarMin":18.54,"rMarMax":22.26},"12095015300":{"TID":"12095015300","RID":68,"tEst":"20","rEst":"20.4","tMar":"3.95","rMar":"1.86","tCV":"0.12","rCV":"0.0555","tMarMin":16.05,"tMarMax":23.95,"rMarMin":18.54,"rMarMax":22.26},"12095016509":{"TID":"12095016509","RID":69,"tEst":"29.3","rEst":"29.6","tMar":"7.14","rMar":"4.97","tCV":"0.148","rCV":"0.102","tMarMin":22.16,"tMarMax":36.44,"rMarMin":24.63,"rMarMax":34.57},"12095016729":{"TID":"12095016729","RID":69,"tEst":"29.7","rEst":"29.6","tMar":"6.05","rMar":"4.97","tCV":"0.124","rCV":"0.102","tMarMin":23.65,"tMarMax":35.75,"rMarMin":24.63,"rMarMax":34.57},"12095016503":{"TID":"12095016503","RID":70,"tEst":"26","rEst":"26.2","tMar":"6.96","rMar":"5.1","tCV":"0.162","rCV":"0.119","tMarMin":19.04,"tMarMax":32.96,"rMarMin":21.1,"rMarMax":31.3},"12095016507":{"TID":"12095016507","RID":70,"tEst":"26.2","rEst":"26.2","tMar":"6.78","rMar":"5.1","tCV":"0.157","rCV":"0.119","tMarMin":19.42,"tMarMax":32.98,"rMarMin":21.1,"rMarMax":31.3},"12095010200":{"TID":"12095010200","RID":71,"tEst":"17.6","rEst":"20.2","tMar":"5.25","rMar":"2.75","tCV":"0.182","rCV":"0.0826","tMarMin":12.35,"tMarMax":22.85,"rMarMin":17.45,"rMarMax":22.95},"12095010300":{"TID":"12095010300","RID":71,"tEst":"22.2","rEst":"20.2","tMar":"5.53","rMar":"2.75","tCV":"0.152","rCV":"0.0826","tMarMin":16.67,"tMarMax":27.73,"rMarMin":17.45,"rMarMax":22.95},"12095013900":{"TID":"12095013900","RID":71,"tEst":"20.9","rEst":"20.2","tMar":"4.23","rMar":"2.75","tCV":"0.123","rCV":"0.0826","tMarMin":16.67,"tMarMax":25.13,"rMarMin":17.45,"rMarMax":22.95},"12095018500":{"TID":"12095018500","RID":71,"tEst":"22.9","rEst":"20.2","tMar":"5.27","rMar":"2.75","tCV":"0.14","rCV":"0.0826","tMarMin":17.63,"tMarMax":28.17,"rMarMin":17.45,"rMarMax":22.95},"12069031307":{"TID":"12069031307","RID":72,"tEst":"27.7","rEst":"27.7","tMar":"4.21","rMar":"4.21","tCV":"0.0922","rCV":"0.0922","tMarMin":23.49,"tMarMax":31.91,"rMarMin":23.49,"rMarMax":31.91},"12117021506":{"TID":"12117021506","RID":73,"tEst":"23.5","rEst":"23.5","tMar":"4.37","rMar":"4.37","tCV":"0.113","rCV":"0.113","tMarMin":19.13,"tMarMax":27.87,"rMarMin":19.13,"rMarMax":27.87},"12117020500":{"TID":"12117020500","RID":74,"tEst":"25.8","rEst":"26.5","tMar":"11.8","rMar":"4.96","tCV":"0.278","rCV":"0.114","tMarMin":14,"tMarMax":37.6,"rMarMin":21.54,"rMarMax":31.46},"12117020301":{"TID":"12117020301","RID":74,"tEst":"24.4","rEst":"26.5","tMar":"6.84","rMar":"4.96","tCV":"0.17","rCV":"0.114","tMarMin":17.56,"tMarMax":31.24,"rMarMin":21.54,"rMarMax":31.46},"12117020102":{"TID":"12117020102","RID":74,"tEst":"29.2","rEst":"26.5","tMar":"16.1","rMar":"4.96","tCV":"0.335","rCV":"0.114","tMarMin":13.1,"tMarMax":45.3,"rMarMin":21.54,"rMarMax":31.46},"12117020101":{"TID":"12117020101","RID":74,"tEst":"24.7","rEst":"26.5","tMar":"15.4","rMar":"4.96","tCV":"0.378","rCV":"0.114","tMarMin":9.3,"tMarMax":40.1,"rMarMin":21.54,"rMarMax":31.46},"12117020201":{"TID":"12117020201","RID":74,"tEst":"29.2","rEst":"26.5","tMar":"11","rMar":"4.96","tCV":"0.229","rCV":"0.114","tMarMin":18.2,"tMarMax":40.2,"rMarMin":21.54,"rMarMax":31.46},"12069030914":{"TID":"12069030914","RID":75,"tEst":"28.7","rEst":"28.8","tMar":"8.62","rMar":"4.52","tCV":"0.183","rCV":"0.0955","tMarMin":20.08,"tMarMax":37.32,"rMarMin":24.28,"rMarMax":33.32},"12069031000":{"TID":"12069031000","RID":75,"tEst":"28.6","rEst":"28.8","tMar":"5.47","rMar":"4.52","tCV":"0.116","rCV":"0.0955","tMarMin":23.13,"tMarMax":34.07,"rMarMin":24.28,"rMarMax":33.32},"12069030805":{"TID":"12069030805","RID":75,"tEst":"29.5","rEst":"28.8","tMar":"13.5","rMar":"4.52","tCV":"0.278","rCV":"0.0955","tMarMin":16,"tMarMax":43,"rMarMin":24.28,"rMarMax":33.32},"12095017008":{"TID":"12095017008","RID":76,"tEst":"20.5","rEst":"20.5","tMar":"3.2","rMar":"3.2","tCV":"0.0948","rCV":"0.0948","tMarMin":17.3,"tMarMax":23.7,"rMarMin":17.3,"rMarMax":23.7},"12095014608":{"TID":"12095014608","RID":77,"tEst":"21.8","rEst":"24.7","tMar":"4.89","rMar":"3.25","tCV":"0.136","rCV":"0.0801","tMarMin":16.91,"tMarMax":26.69,"rMarMin":21.45,"rMarMax":27.95},"12095014704":{"TID":"12095014704","RID":77,"tEst":"24.2","rEst":"24.7","tMar":"4.76","rMar":"3.25","tCV":"0.12","rCV":"0.0801","tMarMin":19.44,"tMarMax":28.96,"rMarMin":21.45,"rMarMax":27.95},"12095014702":{"TID":"12095014702","RID":77,"tEst":"29.3","rEst":"24.7","tMar":"8.43","rMar":"3.25","tCV":"0.175","rCV":"0.0801","tMarMin":20.87,"tMarMax":37.73,"rMarMin":21.45,"rMarMax":27.95},"12095014703":{"TID":"12095014703","RID":77,"tEst":"21.9","rEst":"24.7","tMar":"4.4","rMar":"3.25","tCV":"0.122","rCV":"0.0801","tMarMin":17.5,"tMarMax":26.3,"rMarMin":21.45,"rMarMax":27.95},"12097043301":{"TID":"12097043301","RID":78,"tEst":"27.3","rEst":"33.5","tMar":"18.4","rMar":"5.94","tCV":"0.408","rCV":"0.108","tMarMin":8.9,"tMarMax":45.7,"rMarMin":27.56,"rMarMax":39.44},"12097043800":{"TID":"12097043800","RID":78,"tEst":"35.9","rEst":"33.5","tMar":"7.41","rMar":"5.94","tCV":"0.125","rCV":"0.108","tMarMin":28.49,"tMarMax":43.31,"rMarMin":27.56,"rMarMax":39.44},"12097043205":{"TID":"12097043205","RID":78,"tEst":"29.3","rEst":"33.5","tMar":"10.8","rMar":"5.94","tCV":"0.224","rCV":"0.108","tMarMin":18.5,"tMarMax":40.1,"rMarMin":27.56,"rMarMax":39.44},"12095016712":{"TID":"12095016712","RID":79,"tEst":"27.5","rEst":"27.5","tMar":"4.4","rMar":"4.4","tCV":"0.0973","rCV":"0.0973","tMarMin":23.1,"tMarMax":31.9,"rMarMin":23.1,"rMarMax":31.9},"12095016602":{"TID":"12095016602","RID":80,"tEst":"34.1","rEst":"34.1","tMar":"5.43","rMar":"5.43","tCV":"0.0967","rCV":"0.0967","tMarMin":28.67,"tMarMax":39.53,"rMarMin":28.67,"rMarMax":39.53},"12117022206":{"TID":"12117022206","RID":81,"tEst":"24.5","rEst":"26.4","tMar":"4.94","rMar":"3.95","tCV":"0.122","rCV":"0.0909","tMarMin":19.56,"tMarMax":29.44,"rMarMin":22.45,"rMarMax":30.35},"12117022208":{"TID":"12117022208","RID":81,"tEst":"27.9","rEst":"26.4","tMar":"9.89","rMar":"3.95","tCV":"0.216","rCV":"0.0909","tMarMin":18.01,"tMarMax":37.79,"rMarMin":22.45,"rMarMax":30.35},"12095016302":{"TID":"12095016302","RID":81,"tEst":"29.1","rEst":"26.4","tMar":"7.45","rMar":"3.95","tCV":"0.156","rCV":"0.0909","tMarMin":21.65,"tMarMax":36.55,"rMarMin":22.45,"rMarMax":30.35},"12117021311":{"TID":"12117021311","RID":82,"tEst":"28","rEst":"31.3","tMar":"8.2","rMar":"5.22","tCV":"0.178","rCV":"0.101","tMarMin":19.8,"tMarMax":36.2,"rMarMin":26.08,"rMarMax":36.52},"12117021313":{"TID":"12117021313","RID":82,"tEst":"31.5","rEst":"31.3","tMar":"8.72","rMar":"5.22","tCV":"0.168","rCV":"0.101","tMarMin":22.78,"tMarMax":40.22,"rMarMin":26.08,"rMarMax":36.52},"12117021201":{"TID":"12117021201","RID":82,"tEst":"34.3","rEst":"31.3","tMar":"9.58","rMar":"5.22","tCV":"0.17","rCV":"0.101","tMarMin":24.72,"tMarMax":43.88,"rMarMin":26.08,"rMarMax":36.52},"12095017805":{"TID":"12095017805","RID":83,"tEst":"25","rEst":"25.3","tMar":"6.34","rMar":"3.83","tCV":"0.154","rCV":"0.092","tMarMin":18.66,"tMarMax":31.34,"rMarMin":21.47,"rMarMax":29.13},"12117020703":{"TID":"12117020703","RID":83,"tEst":"25.5","rEst":"25.3","tMar":"4.8","rMar":"3.83","tCV":"0.115","rCV":"0.092","tMarMin":20.7,"tMarMax":30.3,"rMarMin":21.47,"rMarMax":29.13},"12117021317":{"TID":"12117021317","RID":84,"tEst":"27.4","rEst":"27","tMar":"5.1","rMar":"3.29","tCV":"0.113","rCV":"0.0742","tMarMin":22.3,"tMarMax":32.5,"rMarMin":23.71,"rMarMax":30.29},"12117021315":{"TID":"12117021315","RID":84,"tEst":"26.6","rEst":"27","tMar":"6.02","rMar":"3.29","tCV":"0.137","rCV":"0.0742","tMarMin":20.58,"tMarMax":32.62,"rMarMin":23.71,"rMarMax":30.29},"12117021316":{"TID":"12117021316","RID":84,"tEst":"26.6","rEst":"27","tMar":"5.52","rMar":"3.29","tCV":"0.126","rCV":"0.0742","tMarMin":21.08,"tMarMax":32.12,"rMarMin":23.71,"rMarMax":30.29},"12097042200":{"TID":"12097042200","RID":85,"tEst":"27.5","rEst":"26.2","tMar":"5.86","rMar":"3.33","tCV":"0.13","rCV":"0.0774","tMarMin":21.64,"tMarMax":33.36,"rMarMin":22.87,"rMarMax":29.53},"12097042000":{"TID":"12097042000","RID":85,"tEst":"24.9","rEst":"26.2","tMar":"5.37","rMar":"3.33","tCV":"0.131","rCV":"0.0774","tMarMin":19.53,"tMarMax":30.27,"rMarMin":22.87,"rMarMax":29.53},"12097041900":{"TID":"12097041900","RID":85,"tEst":"25.8","rEst":"26.2","tMar":"5.93","rMar":"3.33","tCV":"0.14","rCV":"0.0774","tMarMin":19.87,"tMarMax":31.73,"rMarMin":22.87,"rMarMax":29.53},"12095015104":{"TID":"12095015104","RID":86,"tEst":"27.7","rEst":"25.1","tMar":"7.65","rMar":"4.96","tCV":"0.168","rCV":"0.12","tMarMin":20.05,"tMarMax":35.35,"rMarMin":20.14,"rMarMax":30.06},"12095015202":{"TID":"12095015202","RID":86,"tEst":"22.5","rEst":"25.1","tMar":"6.12","rMar":"4.96","tCV":"0.166","rCV":"0.12","tMarMin":16.38,"tMarMax":28.62,"rMarMin":20.14,"rMarMax":30.06},"12095014804":{"TID":"12095014804","RID":87,"tEst":"24.9","rEst":"26.8","tMar":"5.02","rMar":"4.66","tCV":"0.122","rCV":"0.106","tMarMin":19.88,"tMarMax":29.92,"rMarMin":22.14,"rMarMax":31.46},"12095014805":{"TID":"12095014805","RID":87,"tEst":"28.7","rEst":"26.8","tMar":"7.92","rMar":"4.66","tCV":"0.168","rCV":"0.106","tMarMin":20.78,"tMarMax":36.62,"rMarMin":22.14,"rMarMax":31.46},"12117021306":{"TID":"12117021306","RID":88,"tEst":"28","rEst":"28","tMar":"5.27","rMar":"5.27","tCV":"0.114","rCV":"0.114","tMarMin":22.73,"tMarMax":33.27,"rMarMin":22.73,"rMarMax":33.27},"12095016803":{"TID":"12095016803","RID":89,"tEst":"22.8","rEst":"23.3","tMar":"5.27","rMar":"3.41","tCV":"0.14","rCV":"0.0888","tMarMin":17.53,"tMarMax":28.07,"rMarMin":19.89,"rMarMax":26.71},"12095017012":{"TID":"12095017012","RID":89,"tEst":"24.6","rEst":"23.3","tMar":"9.08","rMar":"3.41","tCV":"0.224","rCV":"0.0888","tMarMin":15.52,"tMarMax":33.68,"rMarMin":19.89,"rMarMax":26.71},"12095017011":{"TID":"12095017011","RID":89,"tEst":"23","rEst":"23.3","tMar":"4.37","rMar":"3.41","tCV":"0.116","rCV":"0.0888","tMarMin":18.63,"tMarMax":27.37,"rMarMin":19.89,"rMarMax":26.71},"12069031102":{"TID":"12069031102","RID":90,"tEst":"29.8","rEst":"28.8","tMar":"9.03","rMar":"5.15","tCV":"0.184","rCV":"0.109","tMarMin":20.77,"tMarMax":38.83,"rMarMin":23.65,"rMarMax":33.95},"12069031101":{"TID":"12069031101","RID":90,"tEst":"25.9","rEst":"28.8","tMar":"8.32","rMar":"5.15","tCV":"0.195","rCV":"0.109","tMarMin":17.58,"tMarMax":34.22,"rMarMin":23.65,"rMarMax":33.95},"12069031103":{"TID":"12069031103","RID":90,"tEst":"32.5","rEst":"28.8","tMar":"7.77","rMar":"5.15","tCV":"0.146","rCV":"0.109","tMarMin":24.73,"tMarMax":40.27,"rMarMin":23.65,"rMarMax":33.95},"12117020903":{"TID":"12117020903","RID":91,"tEst":"28","rEst":"27.1","tMar":"5.91","rMar":"4.02","tCV":"0.128","rCV":"0.0902","tMarMin":22.09,"tMarMax":33.91,"rMarMin":23.08,"rMarMax":31.12},"12117020302":{"TID":"12117020302","RID":91,"tEst":"21","rEst":"27.1","tMar":"8.5","rMar":"4.02","tCV":"0.246","rCV":"0.0902","tMarMin":12.5,"tMarMax":29.5,"rMarMin":23.08,"rMarMax":31.12},"12117020401":{"TID":"12117020401","RID":91,"tEst":"26.6","rEst":"27.1","tMar":"16.9","rMar":"4.02","tCV":"0.385","rCV":"0.0902","tMarMin":9.7,"tMarMax":43.5,"rMarMin":23.08,"rMarMax":31.12},"12117020902":{"TID":"12117020902","RID":91,"tEst":"26.4","rEst":"27.1","tMar":"9.37","rMar":"4.02","tCV":"0.216","rCV":"0.0902","tMarMin":17.03,"tMarMax":35.77,"rMarMin":23.08,"rMarMax":31.12},"12117020901":{"TID":"12117020901","RID":91,"tEst":"27.9","rEst":"27.1","tMar":"8.12","rMar":"4.02","tCV":"0.177","rCV":"0.0902","tMarMin":19.78,"tMarMax":36.02,"rMarMin":23.08,"rMarMax":31.12},"12095014807":{"TID":"12095014807","RID":92,"tEst":"22.7","rEst":"22.7","tMar":"4.35","rMar":"4.35","tCV":"0.116","rCV":"0.116","tMarMin":18.35,"tMarMax":27.05,"rMarMin":18.35,"rMarMax":27.05},"12095017902":{"TID":"12095017902","RID":93,"tEst":"28.6","rEst":"29.7","tMar":"7.32","rMar":"3.05","tCV":"0.156","rCV":"0.0624","tMarMin":21.28,"tMarMax":35.92,"rMarMin":26.65,"rMarMax":32.75},"12069030902":{"TID":"12069030902","RID":93,"tEst":"31.5","rEst":"29.7","tMar":"5","rMar":"3.05","tCV":"0.0967","rCV":"0.0624","tMarMin":26.5,"tMarMax":36.5,"rMarMin":26.65,"rMarMax":32.75},"12069030203":{"TID":"12069030203","RID":93,"tEst":"28.4","rEst":"29.7","tMar":"5","rMar":"3.05","tCV":"0.107","rCV":"0.0624","tMarMin":23.4,"tMarMax":33.4,"rMarMin":26.65,"rMarMax":32.75},"12095017901":{"TID":"12095017901","RID":93,"tEst":"27.8","rEst":"29.7","tMar":"8.74","rMar":"3.05","tCV":"0.191","rCV":"0.0624","tMarMin":19.06,"tMarMax":36.54,"rMarMin":26.65,"rMarMax":32.75},"12095017016":{"TID":"12095017016","RID":94,"tEst":"21.7","rEst":"23","tMar":"4.78","rMar":"4.12","tCV":"0.134","rCV":"0.109","tMarMin":16.92,"tMarMax":26.48,"rMarMin":18.88,"rMarMax":27.12},"12095017004":{"TID":"12095017004","RID":94,"tEst":"25.3","rEst":"23","tMar":"7.65","rMar":"4.12","tCV":"0.183","rCV":"0.109","tMarMin":17.65,"tMarMax":32.95,"rMarMin":18.88,"rMarMax":27.12},"12117021503":{"TID":"12117021503","RID":95,"tEst":"25.1","rEst":"23.7","tMar":"7.29","rMar":"4.29","tCV":"0.177","rCV":"0.11","tMarMin":17.81,"tMarMax":32.39,"rMarMin":19.41,"rMarMax":27.99},"12117021505":{"TID":"12117021505","RID":95,"tEst":"21.6","rEst":"23.7","tMar":"4.53","rMar":"4.29","tCV":"0.128","rCV":"0.11","tMarMin":17.07,"tMarMax":26.13,"rMarMin":19.41,"rMarMax":27.99},"12117021504":{"TID":"12117021504","RID":95,"tEst":"27.5","rEst":"23.7","tMar":"12.3","rMar":"4.29","tCV":"0.272","rCV":"0.11","tMarMin":15.2,"tMarMax":39.8,"rMarMin":19.41,"rMarMax":27.99},"12117020803":{"TID":"12117020803","RID":96,"tEst":"26.5","rEst":"25.6","tMar":"6.53","rMar":"4.98","tCV":"0.15","rCV":"0.118","tMarMin":19.97,"tMarMax":33.03,"rMarMin":20.62,"rMarMax":30.58},"12117020807":{"TID":"12117020807","RID":96,"tEst":"24.8","rEst":"25.6","tMar":"7.41","rMar":"4.98","tCV":"0.182","rCV":"0.118","tMarMin":17.39,"tMarMax":32.21,"rMarMin":20.62,"rMarMax":30.58},"12095013605":{"TID":"12095013605","RID":97,"tEst":"28.9","rEst":"26.6","tMar":"7.35","rMar":"4.22","tCV":"0.154","rCV":"0.0964","tMarMin":21.55,"tMarMax":36.25,"rMarMin":22.38,"rMarMax":30.82},"12095013607":{"TID":"12095013607","RID":97,"tEst":"25.1","rEst":"26.6","tMar":"5.05","rMar":"4.22","tCV":"0.122","rCV":"0.0964","tMarMin":20.05,"tMarMax":30.15,"rMarMin":22.38,"rMarMax":30.82},"12095011200":{"TID":"12095011200","RID":98,"tEst":"26","rEst":"24.3","tMar":"5.78","rMar":"4.09","tCV":"0.135","rCV":"0.103","tMarMin":20.22,"tMarMax":31.78,"rMarMin":20.21,"rMarMax":28.39},"12095011300":{"TID":"12095011300","RID":98,"tEst":"22.9","rEst":"24.3","tMar":"5.68","rMar":"4.09","tCV":"0.151","rCV":"0.103","tMarMin":17.22,"tMarMax":28.58,"rMarMin":20.21,"rMarMax":28.39},"12095014000":{"TID":"12095014000","RID":99,"tEst":"23.3","rEst":"23.9","tMar":"4.12","rMar":"3.46","tCV":"0.107","rCV":"0.0881","tMarMin":19.18,"tMarMax":27.42,"rMarMin":20.44,"rMarMax":27.36},"12095014100":{"TID":"12095014100","RID":99,"tEst":"24.5","rEst":"23.9","tMar":"5.78","rMar":"3.46","tCV":"0.143","rCV":"0.0881","tMarMin":18.72,"tMarMax":30.28,"rMarMin":20.44,"rMarMax":27.36},"12095014809":{"TID":"12095014809","RID":100,"tEst":"23","rEst":"22.4","tMar":"5.41","rMar":"2.27","tCV":"0.143","rCV":"0.0618","tMarMin":17.59,"tMarMax":28.41,"rMarMin":20.13,"rMarMax":24.67},"12095014811":{"TID":"12095014811","RID":100,"tEst":"19.3","rEst":"22.4","tMar":"3.57","rMar":"2.27","tCV":"0.113","rCV":"0.0618","tMarMin":15.73,"tMarMax":22.87,"rMarMin":20.13,"rMarMax":24.67},"12095017108":{"TID":"12095017108","RID":100,"tEst":"22.3","rEst":"22.4","tMar":"4.69","rMar":"2.27","tCV":"0.128","rCV":"0.0618","tMarMin":17.61,"tMarMax":26.99,"rMarMin":20.13,"rMarMax":24.67},"12095017109":{"TID":"12095017109","RID":100,"tEst":"26.6","rEst":"22.4","tMar":"7.54","rMar":"2.27","tCV":"0.172","rCV":"0.0618","tMarMin":19.06,"tMarMax":34.14,"rMarMin":20.13,"rMarMax":24.67},"12095014813":{"TID":"12095014813","RID":100,"tEst":"21.5","rEst":"22.4","tMar":"6.99","rMar":"2.27","tCV":"0.198","rCV":"0.0618","tMarMin":14.51,"tMarMax":28.49,"rMarMin":20.13,"rMarMax":24.67},"12095014810":{"TID":"12095014810","RID":100,"tEst":"21.4","rEst":"22.4","tMar":"4.36","rMar":"2.27","tCV":"0.124","rCV":"0.0618","tMarMin":17.04,"tMarMax":25.76,"rMarMin":20.13,"rMarMax":24.67},"12095016704":{"TID":"12095016704","RID":101,"tEst":"29.7","rEst":"29.7","tMar":"4.73","rMar":"4.73","tCV":"0.0968","rCV":"0.0968","tMarMin":24.97,"tMarMax":34.43,"rMarMin":24.97,"rMarMax":34.43},"12095016301":{"TID":"12095016301","RID":102,"tEst":"28.3","rEst":"23.3","tMar":"7.53","rMar":"3.33","tCV":"0.162","rCV":"0.0868","tMarMin":20.77,"tMarMax":35.83,"rMarMin":19.97,"rMarMax":26.63},"12095016200":{"TID":"12095016200","RID":102,"tEst":"22.5","rEst":"23.3","tMar":"5.35","rMar":"3.33","tCV":"0.145","rCV":"0.0868","tMarMin":17.15,"tMarMax":27.85,"rMarMin":19.97,"rMarMax":26.63},"12095016001":{"TID":"12095016001","RID":102,"tEst":"15.7","rEst":"23.3","tMar":"6.47","rMar":"3.33","tCV":"0.251","rCV":"0.0868","tMarMin":9.23,"tMarMax":22.17,"rMarMin":19.97,"rMarMax":26.63},"12095016100":{"TID":"12095016100","RID":102,"tEst":"20.4","rEst":"23.3","tMar":"4.61","rMar":"3.33","tCV":"0.138","rCV":"0.0868","tMarMin":15.79,"tMarMax":25.01,"rMarMin":19.97,"rMarMax":26.63},"12097042400":{"TID":"12097042400","RID":103,"tEst":"25.2","rEst":"27.8","tMar":"5.02","rMar":"4.61","tCV":"0.121","rCV":"0.101","tMarMin":20.18,"tMarMax":30.22,"rMarMin":23.19,"rMarMax":32.41},"12097042300":{"TID":"12097042300","RID":103,"tEst":"31.2","rEst":"27.8","tMar":"8.56","rMar":"4.61","tCV":"0.167","rCV":"0.101","tMarMin":22.64,"tMarMax":39.76,"rMarMin":23.19,"rMarMax":32.41},"12095012306":{"TID":"12095012306","RID":104,"tEst":"29.9","rEst":"30.5","tMar":"7.37","rMar":"5.93","tCV":"0.15","rCV":"0.118","tMarMin":22.53,"tMarMax":37.27,"rMarMin":24.57,"rMarMax":36.43},"12095015106":{"TID":"12095015106","RID":104,"tEst":"30.7","rEst":"30.5","tMar":"7.93","rMar":"5.93","tCV":"0.157","rCV":"0.118","tMarMin":22.77,"tMarMax":38.63,"rMarMin":24.57,"rMarMax":36.43},"12095015902":{"TID":"12095015902","RID":105,"tEst":"20.1","rEst":"20.9","tMar":"6.88","rMar":"3.86","tCV":"0.208","rCV":"0.112","tMarMin":13.22,"tMarMax":26.98,"rMarMin":17.04,"rMarMax":24.76},"12095015402":{"TID":"12095015402","RID":105,"tEst":"22.5","rEst":"20.9","tMar":"8.17","rMar":"3.86","tCV":"0.221","rCV":"0.112","tMarMin":14.33,"tMarMax":30.67,"rMarMin":17.04,"rMarMax":24.76},"12095018000":{"TID":"12095018000","RID":105,"tEst":"20.3","rEst":"20.9","tMar":"5.37","rMar":"3.86","tCV":"0.161","rCV":"0.112","tMarMin":14.93,"tMarMax":25.67,"rMarMin":17.04,"rMarMax":24.76},"12095013702":{"TID":"12095013702","RID":106,"tEst":"26","rEst":"26","tMar":"6.36","rMar":"4.77","tCV":"0.148","rCV":"0.112","tMarMin":19.64,"tMarMax":32.36,"rMarMin":21.23,"rMarMax":30.77},"12095018400":{"TID":"12095018400","RID":106,"tEst":"17.5","rEst":"26","tMar":"3.97","rMar":"4.77","tCV":"0.138","rCV":"0.112","tMarMin":13.53,"tMarMax":21.47,"rMarMin":21.23,"rMarMax":30.77},"12095013300":{"TID":"12095013300","RID":106,"tEst":"29.1","rEst":"26","tMar":"10.3","rMar":"4.77","tCV":"0.216","rCV":"0.112","tMarMin":18.8,"tMarMax":39.4,"rMarMin":21.23,"rMarMax":30.77},"12095011100":{"TID":"12095011100","RID":106,"tEst":"26.2","rEst":"26","tMar":"9.8","rMar":"4.77","tCV":"0.227","rCV":"0.112","tMarMin":16.4,"tMarMax":36,"rMarMin":21.23,"rMarMax":30.77},"12095017001":{"TID":"12095017001","RID":107,"tEst":"24.1","rEst":"23.6","tMar":"8.14","rMar":"4.65","tCV":"0.206","rCV":"0.12","tMarMin":15.96,"tMarMax":32.24,"rMarMin":18.95,"rMarMax":28.25},"12095017006":{"TID":"12095017006","RID":107,"tEst":"23.3","rEst":"23.6","tMar":"5.56","rMar":"4.65","tCV":"0.145","rCV":"0.12","tMarMin":17.74,"tMarMax":28.86,"rMarMin":18.95,"rMarMax":28.25},"12095017105":{"TID":"12095017105","RID":108,"tEst":"27.6","rEst":"27.7","tMar":"4","rMar":"2.97","tCV":"0.0879","rCV":"0.065","tMarMin":23.6,"tMarMax":31.6,"rMarMin":24.73,"rMarMax":30.67},"12095014808":{"TID":"12095014808","RID":108,"tEst":"27.8","rEst":"27.7","tMar":"4.42","rMar":"2.97","tCV":"0.0965","rCV":"0.065","tMarMin":23.38,"tMarMax":32.22,"rMarMin":24.73,"rMarMax":30.67},"12095017200":{"TID":"12095017200","RID":109,"tEst":"25.8","rEst":"30.4","tMar":"6.37","rMar":"4.81","tCV":"0.15","rCV":"0.0963","tMarMin":19.43,"tMarMax":32.17,"rMarMin":25.59,"rMarMax":35.21},"12069031301":{"TID":"12069031301","RID":109,"tEst":"33","rEst":"30.4","tMar":"6.69","rMar":"4.81","tCV":"0.123","rCV":"0.0963","tMarMin":26.31,"tMarMax":39.69,"rMarMin":25.59,"rMarMax":35.21},"12095017804":{"TID":"12095017804","RID":110,"tEst":"33.5","rEst":"33.5","tMar":"5.9","rMar":"5.9","tCV":"0.107","rCV":"0.107","tMarMin":27.6,"tMarMax":39.4,"rMarMin":27.6,"rMarMax":39.4},"12097040902":{"TID":"12097040902","RID":111,"tEst":"27.5","rEst":"26.2","tMar":"8.41","rMar":"4.12","tCV":"0.186","rCV":"0.0957","tMarMin":19.09,"tMarMax":35.91,"rMarMin":22.08,"rMarMax":30.32},"12097042100":{"TID":"12097042100","RID":111,"tEst":"25.3","rEst":"26.2","tMar":"3.97","rMar":"4.12","tCV":"0.0955","rCV":"0.0957","tMarMin":21.33,"tMarMax":29.27,"rMarMin":22.08,"rMarMax":30.32},"12069030306":{"TID":"12069030306","RID":112,"tEst":"25.1","rEst":"23.9","tMar":"8.47","rMar":"4.1","tCV":"0.205","rCV":"0.104","tMarMin":16.63,"tMarMax":33.57,"rMarMin":19.8,"rMarMax":28},"12069030406":{"TID":"12069030406","RID":112,"tEst":"20.5","rEst":"23.9","tMar":"6.81","rMar":"4.1","tCV":"0.202","rCV":"0.104","tMarMin":13.69,"tMarMax":27.31,"rMarMin":19.8,"rMarMax":28},"12069030305":{"TID":"12069030305","RID":112,"tEst":"26.7","rEst":"23.9","tMar":"8.9","rMar":"4.1","tCV":"0.203","rCV":"0.104","tMarMin":17.8,"tMarMax":35.6,"rMarMin":19.8,"rMarMax":28},"12069030410":{"TID":"12069030410","RID":112,"tEst":"25.7","rEst":"23.9","tMar":"9.03","rMar":"4.1","tCV":"0.213","rCV":"0.104","tMarMin":16.67,"tMarMax":34.73,"rMarMin":19.8,"rMarMax":28},"12095015901":{"TID":"12095015901","RID":113,"tEst":"18.3","rEst":"20.4","tMar":"6.82","rMar":"3.52","tCV":"0.226","rCV":"0.105","tMarMin":11.48,"tMarMax":25.12,"rMarMin":16.88,"rMarMax":23.92},"12095015501":{"TID":"12095015501","RID":113,"tEst":"21.7","rEst":"20.4","tMar":"4.82","rMar":"3.52","tCV":"0.135","rCV":"0.105","tMarMin":16.88,"tMarMax":26.52,"rMarMin":16.88,"rMarMax":23.92},"12117021805":{"TID":"12117021805","RID":113,"tEst":"19.6","rEst":"20.4","tMar":"7.6","rMar":"3.52","tCV":"0.236","rCV":"0.105","tMarMin":12,"tMarMax":27.2,"rMarMin":16.88,"rMarMax":23.92},"12095014200":{"TID":"12095014200","RID":114,"tEst":"24.3","rEst":"24.3","tMar":"4.58","rMar":"4.58","tCV":"0.114","rCV":"0.114","tMarMin":19.72,"tMarMax":28.88,"rMarMin":19.72,"rMarMax":28.88},"12095016730":{"TID":"12095016730","RID":115,"tEst":"32.8","rEst":"32.5","tMar":"3.99","rMar":"3.56","tCV":"0.0739","rCV":"0.0664","tMarMin":28.81,"tMarMax":36.79,"rMarMin":28.94,"rMarMax":36.06},"12095016728":{"TID":"12095016728","RID":115,"tEst":"30.8","rEst":"32.5","tMar":"6.9","rMar":"3.56","tCV":"0.136","rCV":"0.0664","tMarMin":23.9,"tMarMax":37.7,"rMarMin":28.94,"rMarMax":36.06},"12097043500":{"TID":"12097043500","RID":116,"tEst":"32.5","rEst":"34.6","tMar":"7.21","rMar":"3.45","tCV":"0.135","rCV":"0.0607","tMarMin":25.29,"tMarMax":39.71,"rMarMin":31.15,"rMarMax":38.05},"12097043302":{"TID":"12097043302","RID":116,"tEst":"35.3","rEst":"34.6","tMar":"3.92","rMar":"3.45","tCV":"0.0675","rCV":"0.0607","tMarMin":31.38,"tMarMax":39.22,"rMarMin":31.15,"rMarMax":38.05},"12069031310":{"TID":"12069031310","RID":117,"tEst":"37.5","rEst":"36.5","tMar":"7.45","rMar":"5.99","tCV":"0.121","rCV":"0.0999","tMarMin":30.05,"tMarMax":44.95,"rMarMin":30.51,"rMarMax":42.49},"12069031308":{"TID":"12069031308","RID":117,"tEst":"32.7","rEst":"36.5","tMar":"7.26","rMar":"5.99","tCV":"0.135","rCV":"0.0999","tMarMin":25.44,"tMarMax":39.96,"rMarMin":30.51,"rMarMax":42.49},"12097042500":{"TID":"12097042500","RID":118,"tEst":"27.2","rEst":"27.2","tMar":"4.31","rMar":"4.31","tCV":"0.0962","rCV":"0.0962","tMarMin":22.89,"tMarMax":31.51,"rMarMin":22.89,"rMarMax":31.51},"12095016717":{"TID":"12095016717","RID":119,"tEst":"24.4","rEst":"24.4","tMar":"4.01","rMar":"4.01","tCV":"0.1","rCV":"0.1","tMarMin":20.39,"tMarMax":28.41,"rMarMin":20.39,"rMarMax":28.41},"12117021404":{"TID":"12117021404","RID":120,"tEst":"26.1","rEst":"26.1","tMar":"4.05","rMar":"4.05","tCV":"0.0943","rCV":"0.0943","tMarMin":22.05,"tMarMax":30.15,"rMarMin":22.05,"rMarMax":30.15},"12097041001":{"TID":"12097041001","RID":121,"tEst":"33","rEst":"31.7","tMar":"7.27","rMar":"5.18","tCV":"0.134","rCV":"0.0993","tMarMin":25.73,"tMarMax":40.27,"rMarMin":26.52,"rMarMax":36.88},"12097041002":{"TID":"12097041002","RID":121,"tEst":"30.4","rEst":"31.7","tMar":"7.35","rMar":"5.18","tCV":"0.147","rCV":"0.0993","tMarMin":23.05,"tMarMax":37.75,"rMarMin":26.52,"rMarMax":36.88},"12095012402":{"TID":"12095012402","RID":122,"tEst":"26.9","rEst":"30.5","tMar":"7.85","rMar":"2.49","tCV":"0.177","rCV":"0.0496","tMarMin":19.05,"tMarMax":34.75,"rMarMin":28.01,"rMarMax":32.99},"12095012202":{"TID":"12095012202","RID":122,"tEst":"32.3","rEst":"30.5","tMar":"7.34","rMar":"2.49","tCV":"0.138","rCV":"0.0496","tMarMin":24.96,"tMarMax":39.64,"rMarMin":28.01,"rMarMax":32.99},"12095012401":{"TID":"12095012401","RID":122,"tEst":"32.3","rEst":"30.5","tMar":"5.82","rMar":"2.49","tCV":"0.109","rCV":"0.0496","tMarMin":26.48,"tMarMax":38.12,"rMarMin":28.01,"rMarMax":32.99},"12095014908":{"TID":"12095014908","RID":122,"tEst":"29.3","rEst":"30.5","tMar":"8.13","rMar":"2.49","tCV":"0.169","rCV":"0.0496","tMarMin":21.17,"tMarMax":37.43,"rMarMin":28.01,"rMarMax":32.99},"12095012305":{"TID":"12095012305","RID":122,"tEst":"28.1","rEst":"30.5","tMar":"7.12","rMar":"2.49","tCV":"0.154","rCV":"0.0496","tMarMin":20.98,"tMarMax":35.22,"rMarMin":28.01,"rMarMax":32.99},"12095012403":{"TID":"12095012403","RID":122,"tEst":"29.1","rEst":"30.5","tMar":"8.65","rMar":"2.49","tCV":"0.181","rCV":"0.0496","tMarMin":20.45,"tMarMax":37.75,"rMarMin":28.01,"rMarMax":32.99},"12095012307":{"TID":"12095012307","RID":122,"tEst":"32.9","rEst":"30.5","tMar":"8.65","rMar":"2.49","tCV":"0.16","rCV":"0.0496","tMarMin":24.25,"tMarMax":41.55,"rMarMin":28.01,"rMarMax":32.99},"12095014904":{"TID":"12095014904","RID":122,"tEst":"28.7","rEst":"30.5","tMar":"6.45","rMar":"2.49","tCV":"0.137","rCV":"0.0496","tMarMin":22.25,"tMarMax":35.15,"rMarMin":28.01,"rMarMax":32.99},"12095012201":{"TID":"12095012201","RID":122,"tEst":"35.7","rEst":"30.5","tMar":"10.2","rMar":"2.49","tCV":"0.173","rCV":"0.0496","tMarMin":25.5,"tMarMax":45.9,"rMarMin":28.01,"rMarMax":32.99},"12095012100":{"TID":"12095012100","RID":122,"tEst":"28.8","rEst":"30.5","tMar":"8.22","rMar":"2.49","tCV":"0.173","rCV":"0.0496","tMarMin":20.58,"tMarMax":37.02,"rMarMin":28.01,"rMarMax":32.99},"12117021706":{"TID":"12117021706","RID":123,"tEst":"22.6","rEst":"24","tMar":"8.21","rMar":"4.17","tCV":"0.22","rCV":"0.106","tMarMin":14.39,"tMarMax":30.81,"rMarMin":19.83,"rMarMax":28.17},"12095015201":{"TID":"12095015201","RID":123,"tEst":"24.4","rEst":"24","tMar":"4.82","rMar":"4.17","tCV":"0.12","rCV":"0.106","tMarMin":19.58,"tMarMax":29.22,"rMarMin":19.83,"rMarMax":28.17},"12095015004":{"TID":"12095015004","RID":124,"tEst":"28.9","rEst":"28.9","tMar":"5.5","rMar":"5.5","tCV":"0.116","rCV":"0.116","tMarMin":23.4,"tMarMax":34.4,"rMarMin":23.4,"rMarMax":34.4},"12095017501":{"TID":"12095017501","RID":125,"tEst":"27.1","rEst":"28.6","tMar":"5.36","rMar":"3.68","tCV":"0.12","rCV":"0.0783","tMarMin":21.74,"tMarMax":32.46,"rMarMin":24.92,"rMarMax":32.28},"12095017600":{"TID":"12095017600","RID":125,"tEst":"31.5","rEst":"28.6","tMar":"10.9","rMar":"3.68","tCV":"0.21","rCV":"0.0783","tMarMin":20.6,"tMarMax":42.4,"rMarMin":24.92,"rMarMax":32.28},"12095015002":{"TID":"12095015002","RID":125,"tEst":"33.4","rEst":"28.6","tMar":"10.1","rMar":"3.68","tCV":"0.184","rCV":"0.0783","tMarMin":23.3,"tMarMax":43.5,"rMarMin":24.92,"rMarMax":32.28},"12095017503":{"TID":"12095017503","RID":125,"tEst":"25.4","rEst":"28.6","tMar":"6.17","rMar":"3.68","tCV":"0.147","rCV":"0.0783","tMarMin":19.23,"tMarMax":31.57,"rMarMin":24.92,"rMarMax":32.28},"12095015001":{"TID":"12095015001","RID":125,"tEst":"22.6","rEst":"28.6","tMar":"11.2","rMar":"3.68","tCV":"0.302","rCV":"0.0783","tMarMin":11.4,"tMarMax":33.8,"rMarMin":24.92,"rMarMax":32.28},"12095014906":{"TID":"12095014906","RID":126,"tEst":"27","rEst":"26.5","tMar":"5.62","rMar":"4.09","tCV":"0.127","rCV":"0.0938","tMarMin":21.38,"tMarMax":32.62,"rMarMin":22.41,"rMarMax":30.59},"12095015003":{"TID":"12095015003","RID":126,"tEst":"27.3","rEst":"26.5","tMar":"8.42","rMar":"4.09","tCV":"0.187","rCV":"0.0938","tMarMin":18.88,"tMarMax":35.72,"rMarMin":22.41,"rMarMax":30.59},"12095018100":{"TID":"12095018100","RID":126,"tEst":"24.2","rEst":"26.5","tMar":"5.09","rMar":"4.09","tCV":"0.128","rCV":"0.0938","tMarMin":19.11,"tMarMax":29.29,"rMarMin":22.41,"rMarMax":30.59},"12095014504":{"TID":"12095014504","RID":127,"tEst":"19.7","rEst":"20.5","tMar":"6.65","rMar":"2.83","tCV":"0.205","rCV":"0.0841","tMarMin":13.05,"tMarMax":26.35,"rMarMin":17.67,"rMarMax":23.33},"12095014607":{"TID":"12095014607","RID":127,"tEst":"22.2","rEst":"20.5","tMar":"4.64","rMar":"2.83","tCV":"0.127","rCV":"0.0841","tMarMin":17.56,"tMarMax":26.84,"rMarMin":17.67,"rMarMax":23.33},"12095014812":{"TID":"12095014812","RID":127,"tEst":"19.4","rEst":"20.5","tMar":"3.73","rMar":"2.83","tCV":"0.117","rCV":"0.0841","tMarMin":15.67,"tMarMax":23.13,"rMarMin":17.67,"rMarMax":23.33},"12095015103":{"TID":"12095015103","RID":128,"tEst":"24.2","rEst":"24.7","tMar":"3.49","rMar":"3.43","tCV":"0.0878","rCV":"0.0846","tMarMin":20.71,"tMarMax":27.69,"rMarMin":21.27,"rMarMax":28.13},"12095015105":{"TID":"12095015105","RID":128,"tEst":"25.7","rEst":"24.7","tMar":"7.82","rMar":"3.43","tCV":"0.185","rCV":"0.0846","tMarMin":17.88,"tMarMax":33.52,"rMarMin":21.27,"rMarMax":28.13},"12095016734":{"TID":"12095016734","RID":129,"tEst":"31.8","rEst":"31.5","tMar":"6.57","rMar":"4.62","tCV":"0.126","rCV":"0.0893","tMarMin":25.23,"tMarMax":38.37,"rMarMin":26.88,"rMarMax":36.12},"12095016709":{"TID":"12095016709","RID":129,"tEst":"31","rEst":"31.5","tMar":"6.05","rMar":"4.62","tCV":"0.118","rCV":"0.0893","tMarMin":24.95,"tMarMax":37.05,"rMarMin":26.88,"rMarMax":36.12},"12095017701":{"TID":"12095017701","RID":130,"tEst":"29.5","rEst":"29.3","tMar":"5.13","rMar":"3.26","tCV":"0.106","rCV":"0.0676","tMarMin":24.37,"tMarMax":34.63,"rMarMin":26.04,"rMarMax":32.56},"12095017807":{"TID":"12095017807","RID":130,"tEst":"29.2","rEst":"29.3","tMar":"4.59","rMar":"3.26","tCV":"0.0957","rCV":"0.0676","tMarMin":24.61,"tMarMax":33.79,"rMarMin":26.04,"rMarMax":32.56},"12095017703":{"TID":"12095017703","RID":130,"tEst":"29","rEst":"29.3","tMar":"7.07","rMar":"3.26","tCV":"0.148","rCV":"0.0676","tMarMin":21.93,"tMarMax":36.07,"rMarMin":26.04,"rMarMax":32.56},"12095015801":{"TID":"12095015801","RID":131,"tEst":"20.6","rEst":"20.4","tMar":"8.75","rMar":"3.3","tCV":"0.258","rCV":"0.0986","tMarMin":11.85,"tMarMax":29.35,"rMarMin":17.1,"rMarMax":23.7},"12095016002":{"TID":"12095016002","RID":131,"tEst":"19.8","rEst":"20.4","tMar":"6.01","rMar":"3.3","tCV":"0.184","rCV":"0.0986","tMarMin":13.79,"tMarMax":25.81,"rMarMin":17.1,"rMarMax":23.7},"12095015601":{"TID":"12095015601","RID":131,"tEst":"23.2","rEst":"20.4","tMar":"6.54","rMar":"3.3","tCV":"0.171","rCV":"0.0986","tMarMin":16.66,"tMarMax":29.74,"rMarMin":17.1,"rMarMax":23.7},"12095015701":{"TID":"12095015701","RID":131,"tEst":"17.9","rEst":"20.4","tMar":"5.84","rMar":"3.3","tCV":"0.198","rCV":"0.0986","tMarMin":12.06,"tMarMax":23.74,"rMarMin":17.1,"rMarMax":23.7},"12069030502":{"TID":"12069030502","RID":132,"tEst":"14.9","rEst":"17.3","tMar":"3.96","rMar":"2.27","tCV":"0.162","rCV":"0.0797","tMarMin":10.94,"tMarMax":18.86,"rMarMin":15.03,"rMarMax":19.57},"12069030701":{"TID":"12069030701","RID":132,"tEst":"15.6","rEst":"17.3","tMar":"6.39","rMar":"2.27","tCV":"0.25","rCV":"0.0797","tMarMin":9.21,"tMarMax":21.99,"rMarMin":15.03,"rMarMax":19.57},"12069030702":{"TID":"12069030702","RID":132,"tEst":"18.9","rEst":"17.3","tMar":"3.99","rMar":"2.27","tCV":"0.129","rCV":"0.0797","tMarMin":14.91,"tMarMax":22.89,"rMarMin":15.03,"rMarMax":19.57},"12069030308":{"TID":"12069030308","RID":132,"tEst":"18","rEst":"17.3","tMar":"4.67","rMar":"2.27","tCV":"0.157","rCV":"0.0797","tMarMin":13.33,"tMarMax":22.67,"rMarMin":15.03,"rMarMax":19.57},"12069030503":{"TID":"12069030503","RID":132,"tEst":"19.6","rEst":"17.3","tMar":"9.93","rMar":"2.27","tCV":"0.308","rCV":"0.0797","tMarMin":9.67,"tMarMax":29.53,"rMarMin":15.03,"rMarMax":19.57},"12069031305":{"TID":"12069031305","RID":133,"tEst":"25.1","rEst":"29.5","tMar":"6.38","rMar":"5.07","tCV":"0.155","rCV":"0.105","tMarMin":18.72,"tMarMax":31.48,"rMarMin":24.43,"rMarMax":34.57},"12069031309":{"TID":"12069031309","RID":133,"tEst":"31.2","rEst":"29.5","tMar":"9.44","rMar":"5.07","tCV":"0.184","rCV":"0.105","tMarMin":21.76,"tMarMax":40.64,"rMarMin":24.43,"rMarMax":34.57},"12069031204":{"TID":"12069031204","RID":133,"tEst":"30.7","rEst":"29.5","tMar":"8.76","rMar":"5.07","tCV":"0.174","rCV":"0.105","tMarMin":21.94,"tMarMax":39.46,"rMarMin":24.43,"rMarMax":34.57},"12097043600":{"TID":"12097043600","RID":134,"tEst":"34.3","rEst":"34.5","tMar":"8.82","rMar":"6.34","tCV":"0.156","rCV":"0.112","tMarMin":25.48,"tMarMax":43.12,"rMarMin":28.16,"rMarMax":40.84},"12097043700":{"TID":"12097043700","RID":134,"tEst":"34.9","rEst":"34.5","tMar":"8.49","rMar":"6.34","tCV":"0.148","rCV":"0.112","tMarMin":26.41,"tMarMax":43.39,"rMarMin":28.16,"rMarMax":40.84},"12117021203":{"TID":"12117021203","RID":135,"tEst":"32.4","rEst":"32.4","tMar":"7.31","rMar":"6.27","tCV":"0.137","rCV":"0.118","tMarMin":25.09,"tMarMax":39.71,"rMarMin":26.13,"rMarMax":38.67},"12117021319":{"TID":"12117021319","RID":135,"tEst":"32.4","rEst":"32.4","tMar":"12.1","rMar":"6.27","tCV":"0.227","rCV":"0.118","tMarMin":20.3,"tMarMax":44.5,"rMarMin":26.13,"rMarMax":38.67},"12097043206":{"TID":"12097043206","RID":136,"tEst":"24.7","rEst":"30.7","tMar":"20.3","rMar":"4.62","tCV":"0.5","rCV":"0.0914","tMarMin":4.4,"tMarMax":45,"rMarMin":26.08,"rMarMax":35.32},"12097043100":{"TID":"12097043100","RID":136,"tEst":"32.1","rEst":"30.7","tMar":"7.71","rMar":"4.62","tCV":"0.146","rCV":"0.0914","tMarMin":24.39,"tMarMax":39.81,"rMarMin":26.08,"rMarMax":35.32},"12097041500":{"TID":"12097041500","RID":136,"tEst":"30.4","rEst":"30.7","tMar":"5.78","rMar":"4.62","tCV":"0.115","rCV":"0.0914","tMarMin":24.62,"tMarMax":36.18,"rMarMin":26.08,"rMarMax":35.32},"12095012900":{"TID":"12095012900","RID":137,"tEst":"22","rEst":"20.4","tMar":"4.82","rMar":"2.97","tCV":"0.133","rCV":"0.0884","tMarMin":17.18,"tMarMax":26.82,"rMarMin":17.43,"rMarMax":23.37},"12095010802":{"TID":"12095010802","RID":137,"tEst":"18.8","rEst":"20.4","tMar":"3.49","rMar":"2.97","tCV":"0.113","rCV":"0.0884","tMarMin":15.31,"tMarMax":22.29,"rMarMin":17.43,"rMarMax":23.37},"12095016807":{"TID":"12095016807","RID":138,"tEst":"27.7","rEst":"27.3","tMar":"5.18","rMar":"3.8","tCV":"0.114","rCV":"0.0845","tMarMin":22.52,"tMarMax":32.88,"rMarMin":23.5,"rMarMax":31.1},"12095016806":{"TID":"12095016806","RID":138,"tEst":"26.8","rEst":"27.3","tMar":"5.43","rMar":"3.8","tCV":"0.123","rCV":"0.0845","tMarMin":21.37,"tMarMax":32.23,"rMarMin":23.5,"rMarMax":31.1},"12095016410":{"TID":"12095016410","RID":139,"tEst":"27.1","rEst":"27.1","tMar":"4.99","rMar":"4.99","tCV":"0.112","rCV":"0.112","tMarMin":22.11,"tMarMax":32.09,"rMarMin":22.11,"rMarMax":32.09},"12097042701":{"TID":"12097042701","RID":140,"tEst":"27.9","rEst":"28.2","tMar":"5.85","rMar":"4.4","tCV":"0.127","rCV":"0.0948","tMarMin":22.05,"tMarMax":33.75,"rMarMin":23.8,"rMarMax":32.6},"12097042702":{"TID":"12097042702","RID":140,"tEst":"28.5","rEst":"28.2","tMar":"6.59","rMar":"4.4","tCV":"0.141","rCV":"0.0948","tMarMin":21.91,"tMarMax":35.09,"rMarMin":23.8,"rMarMax":32.6},"12117022106":{"TID":"12117022106","RID":141,"tEst":"28.7","rEst":"28.4","tMar":"4.94","rMar":"3.99","tCV":"0.105","rCV":"0.0854","tMarMin":23.76,"tMarMax":33.64,"rMarMin":24.41,"rMarMax":32.39},"12117022105":{"TID":"12117022105","RID":141,"tEst":"27.8","rEst":"28.4","tMar":"6.75","rMar":"3.99","tCV":"0.148","rCV":"0.0854","tMarMin":21.05,"tMarMax":34.55,"rMarMin":24.41,"rMarMax":32.39},"12095017400":{"TID":"12095017400","RID":142,"tEst":"24.2","rEst":"24.8","tMar":"4.2","rMar":"3.95","tCV":"0.106","rCV":"0.0968","tMarMin":20,"tMarMax":28.4,"rMarMin":20.85,"rMarMax":28.75},"12095017300":{"TID":"12095017300","RID":142,"tEst":"25.4","rEst":"24.8","tMar":"6.72","rMar":"3.95","tCV":"0.16","rCV":"0.0968","tMarMin":18.68,"tMarMax":32.12,"rMarMin":20.85,"rMarMax":28.75},"12097042800":{"TID":"12097042800","RID":143,"tEst":"30","rEst":"29.7","tMar":"6.29","rMar":"5.42","tCV":"0.127","rCV":"0.111","tMarMin":23.71,"tMarMax":36.29,"rMarMin":24.28,"rMarMax":35.12},"12097042601":{"TID":"12097042601","RID":143,"tEst":"28.5","rEst":"29.7","tMar":"10.7","rMar":"5.42","tCV":"0.228","rCV":"0.111","tMarMin":17.8,"tMarMax":39.2,"rMarMin":24.28,"rMarMax":35.12},"12117021606":{"TID":"12117021606","RID":144,"tEst":"25.9","rEst":"25.1","tMar":"6.48","rMar":"4.58","tCV":"0.152","rCV":"0.111","tMarMin":19.42,"tMarMax":32.38,"rMarMin":20.52,"rMarMax":29.68},"12117021613":{"TID":"12117021613","RID":144,"tEst":"23.8","rEst":"25.1","tMar":"5.63","rMar":"4.58","tCV":"0.144","rCV":"0.111","tMarMin":18.17,"tMarMax":29.43,"rMarMin":20.52,"rMarMax":29.68},"12097041100":{"TID":"12097041100","RID":145,"tEst":"41.3","rEst":"41.3","tMar":"5.98","rMar":"5.98","tCV":"0.088","rCV":"0.088","tMarMin":35.32,"tMarMax":47.28,"rMarMin":35.32,"rMarMax":47.28},"12095017104":{"TID":"12095017104","RID":146,"tEst":"25.5","rEst":"25.5","tMar":"2.78","rMar":"2.78","tCV":"0.0662","rCV":"0.0662","tMarMin":22.72,"tMarMax":28.28,"rMarMin":22.72,"rMarMax":28.28},"12095016407":{"TID":"12095016407","RID":147,"tEst":"24.8","rEst":"24.1","tMar":"6.22","rMar":"4.55","tCV":"0.153","rCV":"0.115","tMarMin":18.58,"tMarMax":31.02,"rMarMin":19.55,"rMarMax":28.65},"12095013202":{"TID":"12095013202","RID":147,"tEst":"23.6","rEst":"24.1","tMar":"6.5","rMar":"4.55","tCV":"0.167","rCV":"0.115","tMarMin":17.1,"tMarMax":30.1,"rMarMin":19.55,"rMarMax":28.65},"12117020805":{"TID":"12117020805","RID":148,"tEst":"25.7","rEst":"26.7","tMar":"5.35","rMar":"4.63","tCV":"0.127","rCV":"0.105","tMarMin":20.35,"tMarMax":31.05,"rMarMin":22.07,"rMarMax":31.33},"12117020806":{"TID":"12117020806","RID":148,"tEst":"27.7","rEst":"26.7","tMar":"7.57","rMar":"4.63","tCV":"0.166","rCV":"0.105","tMarMin":20.13,"tMarMax":35.27,"rMarMin":22.07,"rMarMax":31.33},"12095016710":{"TID":"12095016710","RID":149,"tEst":"29.9","rEst":"29.9","tMar":"5.3","rMar":"5.3","tCV":"0.108","rCV":"0.108","tMarMin":24.6,"tMarMax":35.2,"rMarMin":24.6,"rMarMax":35.2},"12095017702":{"TID":"12095017702","RID":150,"tEst":"35.4","rEst":"30.6","tMar":"10.7","rMar":"4.91","tCV":"0.183","rCV":"0.0977","tMarMin":24.7,"tMarMax":46.1,"rMarMin":25.69,"rMarMax":35.51},"12095017806":{"TID":"12095017806","RID":150,"tEst":"28.1","rEst":"30.6","tMar":"4.97","rMar":"4.91","tCV":"0.107","rCV":"0.0977","tMarMin":23.13,"tMarMax":33.07,"rMarMin":25.69,"rMarMax":35.51},"12117021403":{"TID":"12117021403","RID":151,"tEst":"26.6","rEst":"26","tMar":"4.48","rMar":"3.5","tCV":"0.102","rCV":"0.0816","tMarMin":22.12,"tMarMax":31.08,"rMarMin":22.5,"rMarMax":29.5},"12117021000":{"TID":"12117021000","RID":151,"tEst":"24.9","rEst":"26","tMar":"5.49","rMar":"3.5","tCV":"0.134","rCV":"0.0816","tMarMin":19.41,"tMarMax":30.39,"rMarMin":22.5,"rMarMax":29.5},"12095016713":{"TID":"12095016713","RID":152,"tEst":"26.7","rEst":"25.6","tMar":"5.48","rMar":"4.22","tCV":"0.125","rCV":"0.1","tMarMin":21.22,"tMarMax":32.18,"rMarMin":21.38,"rMarMax":29.82},"12095016411":{"TID":"12095016411","RID":152,"tEst":"23.7","rEst":"25.6","tMar":"6.47","rMar":"4.22","tCV":"0.166","rCV":"0.1","tMarMin":17.23,"tMarMax":30.17,"rMarMin":21.38,"rMarMax":29.82},"12095017015":{"TID":"12095017015","RID":153,"tEst":"27.2","rEst":"26.6","tMar":"5.8","rMar":"4.26","tCV":"0.13","rCV":"0.0974","tMarMin":21.4,"tMarMax":33,"rMarMin":22.34,"rMarMax":30.86},"12095017014":{"TID":"12095017014","RID":153,"tEst":"26.3","rEst":"26.6","tMar":"5.84","rMar":"4.26","tCV":"0.135","rCV":"0.0974","tMarMin":20.46,"tMarMax":32.14,"rMarMin":22.34,"rMarMax":30.86}}